[
  {
    "ami_id": "ami-0e8259988e4aef2f7",
    "architecture": "x86_64",
    "description": "Amazon Linux 2 AMI 2.0.20241217.0 x86_64 HVM gp2",
    "hypervisor": "xen",
    "image_type": "machine",
    "name": "amzn2-ami-hvm-2.0.20241217.0-x86_64-gp2",
    "owner_id": "071630900071",
    "platform": null,
    "public": true,
    "root_device_name": "/dev/xvda",
    "root_device_type": "ebs",
    "sriov": "simple",
    "state": "available",
    "virtualization_type": "hvm"
  },
  {
    "ami_id": "ami-08d51e5b1495de432",
    "architecture": "x86_64",
    "description": "Amazon Linux 2 Kernel 5.10 AMI 2.0.20241217.0 x86_64 HVM gp2",
    "hypervisor": "xen",
    "image_type": "machine",
    "name": "amzn2-ami-kernel-5.10-hvm-2.0.20241217.0-x86_64-gp2",
    "owner_id": "071630900071",
    "platform": null,
    "public": true,
    "root_device_name": "/dev/xvda",
    "root_device_type": "ebs",
    "sriov": "simple",
    "state": "available",
    "virtualization_type": "hvm"
  },
  {
    "ami_id": "ami-0ccf3af4cc689f00f",
    "architecture": "x86_64",
    "description": "Amazon Linux 2 AMI 2.0.20241217.0 x86_64 Minimal HVM ebs",
    "hypervisor": "xen",
    "image_type": "machine",
    "name": "amzn2-ami-minimal-hvm-2.0.20241217.0-x86_64-ebs",
    "owner_id": "071630900071",
    "platform": null,
    "public": true,
    "root_device_name": "/dev/xvda",
    "root_device_type": "ebs",
    "sriov": "simple",
    "state": "available",
    "virtualization_type": "hvm"
  },
  {
    "ami_id": "ami-03dc071bffd30bfb1",
    "architecture": "arm64",
    "description": "Amazon Linux 2023 AMI 2023.6.20241212.0 arm64 HVM kernel-6.1",
    "hypervisor": "xen",
    "image_type": "machine",
    "name": "al2023-ami-2023.6.20241212.0-kernel-6.1-arm64",
    "owner_id": "071630900071",
    "platform": null,
    "public": true,
    "root_device_name": "/dev/xvda",
    "root_device_type": "ebs",
    "sriov": "simple",
    "state": "available",
    "virtualization_type": "hvm"
  },
  {
    "ami_id": "ami-0fe5ba4cecc406c59",
    "architecture": "arm64",
    "description": "Amazon Linux 2023 AMI 2023.6.20241212.0 arm64 Minimal HVM kernel-6.1",
    "hypervisor": "xen",
    "image_type": "machine",
    "name": "al2023-ami-minimal-2023.6.20241212.0-kernel-6.1-arm64",
    "owner_id": "071630900071",
    "platform": null,
    "public": true,
    "root_device_name": "/dev/xvda",
    "root_device_type": "ebs",
    "sriov": "simple",
    "state": "available",
    "virtualization_type": "hvm"
  },
  {
    "ami_id": "ami-076a1cb1773a8ebe4",
    "architecture": "x86_64",
    "description": "Amazon Linux AMI 2018.03.0.20231218.0 x86_64 HVM ebs",
    "hypervisor": "xen",
    "image_type": "machine",
    "name": "amzn-ami-hvm-2018.03.0.20231218.0-x86_64-ebs",
    "owner_id": "071630900071",
    "platform": null,
    "public": true,
    "root_device_name": "/dev/xvda",
    "root_device_type": "ebs",
    "sriov": "simple",
    "state": "available",
    "virtualization_type": "hvm"
  },
  {
    "ami_id": "ami-0e1302181c8b9a346",
    "architecture": "x86_64",
    "description": "Amazon Linux 2023 AMI 2023.6.20241212.0 x86_64 Minimal HVM kernel-6.1",
    "hypervisor": "xen",
    "image_type": "machine",
    "name": "al2023-ami-minimal-2023.6.20241212.0-kernel-6.1-x86_64",
    "owner_id": "071630900071",
    "platform": null,
    "public": true,
    "root_device_name": "/dev/xvda",
    "root_device_type": "ebs",
    "sriov": "simple",
    "state": "available",
    "virtualization_type": "hvm"
  },
  {
    "ami_id": "ami-06d09ff1b3d71d720",
    "architecture": "x86_64",
    "description": "Amazon Linux AMI 2018.03.0.20231218.0 x86_64 Minimal HVM ebs",
    "hypervisor": "xen",
    "image_type": "machine",
    "name": "amzn-ami-minimal-hvm-2018.03.0.20231218.0-x86_64-ebs",
    "owner_id": "071630900071",
    "platform": null,
    "public": true,
    "root_device_name": "/dev/xvda",
    "root_device_type": "ebs",
    "sriov": "simple",
    "state": "available",
    "virtualization_type": "hvm"
  },
  {
    "ami_id": "ami-059fb359855601713",
    "architecture": "arm64",
    "description": "Amazon Linux 2 LTS Arm64 Kernel 5.10 AMI 2.0.20241217.0 arm64 HVM gp2",
    "hypervisor": "xen",
    "image_type": "machine",
    "name": "amzn2-ami-kernel-5.10-hvm-2.0.20241217.0-arm64-gp2",
    "owner_id": "071630900071",
    "platform": null,
    "public": true,
    "root_device_name": "/dev/xvda",
    "root_device_type": "ebs",
    "sriov": "simple",
    "state": "available",
    "virtualization_type": "hvm"
  },
  {
    "ami_id": "ami-0799a07c2e7bd0d8e",
    "architecture": "x86_64",
    "description": "Amazon Linux AMI 2018.03.0.20231218.0 x86_64 HVM gp2",
    "hypervisor": "xen",
    "image_type": "machine",
    "name": "amzn-ami-hvm-2018.03.0.20231218.0-x86_64-gp2",
    "owner_id": "071630900071",
    "platform": null,
    "public": true,
    "root_device_name": "/dev/xvda",
    "root_device_type": "ebs",
    "sriov": "simple",
    "state": "available",
    "virtualization_type": "hvm"
  },
  {
    "ami_id": "ami-0f529654669a607d1",
    "architecture": "x86_64",
    "description": "Amazon Linux 2023 AMI 2023.6.20241212.0 x86_64 HVM kernel-6.1",
    "hypervisor": "xen",
    "image_type": "machine",
    "name": "al2023-ami-2023.6.20241212.0-kernel-6.1-x86_64",
    "owner_id": "071630900071",
    "platform": null,
    "public": true,
    "root_device_name": "/dev/xvda",
    "root_device_type": "ebs",
    "sriov": "simple",
    "state": "available",
    "virtualization_type": "hvm"
  },
  {
    "ami_id": "ami-0d8fbf2e25a2806fb",
    "architecture": "arm64",
    "description": "Amazon Linux 2 LTS Arm64 AMI 2.0.20241217.0 arm64 HVM gp2",
    "hypervisor": "xen",
    "image_type": "machine",
    "name": "amzn2-ami-hvm-2.0.20241217.0-arm64-gp2",
    "owner_id": "071630900071",
    "platform": null,
    "public": true,
    "root_device_name": "/dev/xvda",
    "root_device_type": "ebs",
    "sriov": "simple",
    "state": "available",
    "virtualization_type": "hvm"
  },
  {
    "ami_id": "ami-08b9ada1595d146d2",
    "architecture": "x86_64",
    "description": "Amazon Linux 2 AMI 2.0.20241217.0 x86_64 HVM ebs",
    "hypervisor": "xen",
    "image_type": "machine",
    "name": "amzn2-ami-hvm-2.0.20241217.0-x86_64-ebs",
    "owner_id": "071630900071",
    "platform": null,
    "public": true,
    "root_device_name": "/dev/xvda",
    "root_device_type": "ebs",
    "sriov": "simple",
    "state": "available",
    "virtualization_type": "hvm"
  },
  {
    "ami_id": "ami-07c647562a2317365",
    "architecture": "x86_64",
    "description": "Amazon Linux 2 Kernel 5.10 AMI 2.0.20241217.0 x86_64 HVM ebs",
    "hypervisor": "xen",
    "image_type": "machine",
    "name": "amzn2-ami-kernel-5.10-hvm-2.0.20241217.0-x86_64-ebs",
    "owner_id": "071630900071",
    "platform": null,
    "public": true,
    "root_device_name": "/dev/xvda",
    "root_device_type": "ebs",
    "sriov": "simple",
    "state": "available",
    "virtualization_type": "hvm"
  },
  {
    "ami_id": "ami-0240f8c365db4c4d8",
    "architecture": "arm64",
    "description": "Amazon Linux 2 LTS Arm64 AMI 2.0.20241217.0 arm64 Minimal HVM ebs",
    "hypervisor": "xen",
    "image_type": "machine",
    "name": "amzn2-ami-minimal-hvm-2.0.20241217.0-arm64-ebs",
    "owner_id": "071630900071",
    "platform": null,
    "public": true,
    "root_device_name": "/dev/xvda",
    "root_device_type": "ebs",
    "sriov": "simple",
    "state": "available",
    "virtualization_type": "hvm"
  }
]