[
  {
    "ami_id": "ami-04d6254e8a1ca0927",
    "architecture": "x86_64",
    "description": "Amazon Linux 2023 AMI 2023.11.20260427.1 x86_64 HVM kernel-6.18",
    "hypervisor": "xen",
    "image_type": "machine",
    "name": "al2023-ami-2023.11.20260427.1-kernel-6.18-x86_64",
    "owner_id": "137112412989",
    "platform": null,
    "public": true,
    "root_device_name": "/dev/xvda",
    "root_device_type": "ebs",
    "sriov": "simple",
    "state": "available",
    "tags": {},
    "virtualization_type": "hvm"
  },
  {
    "ami_id": "ami-073dbb3a8a8f7ff21",
    "architecture": "arm64",
    "description": "Amazon Linux 2 LTS Arm64 AMI 2.0.20260427.1 arm64 HVM gp2",
    "hypervisor": "xen",
    "image_type": "machine",
    "name": "amzn2-ami-hvm-2.0.20260427.1-arm64-gp2",
    "owner_id": "137112412989",
    "platform": null,
    "public": true,
    "root_device_name": "/dev/xvda",
    "root_device_type": "ebs",
    "sriov": "simple",
    "state": "available",
    "tags": {},
    "virtualization_type": "hvm"
  },
  {
    "ami_id": "ami-077bf0f775cb6d0a3",
    "architecture": "arm64",
    "description": "Amazon Linux 2 LTS Arm64 Kernel 5.10 AMI 2.0.20260427.1 arm64 HVM gp2",
    "hypervisor": "xen",
    "image_type": "machine",
    "name": "amzn2-ami-kernel-5.10-hvm-2.0.20260427.1-arm64-gp2",
    "owner_id": "137112412989",
    "platform": null,
    "public": true,
    "root_device_name": "/dev/xvda",
    "root_device_type": "ebs",
    "sriov": "simple",
    "state": "available",
    "tags": {},
    "virtualization_type": "hvm"
  },
  {
    "ami_id": "ami-05328bcf42a046dde",
    "architecture": "arm64",
    "description": "Amazon Linux 2023 AMI 2023.11.20260427.1 arm64 HVM kernel-6.12",
    "hypervisor": "xen",
    "image_type": "machine",
    "name": "al2023-ami-2023.11.20260427.1-kernel-6.12-arm64",
    "owner_id": "137112412989",
    "platform": null,
    "public": true,
    "root_device_name": "/dev/xvda",
    "root_device_type": "ebs",
    "sriov": "simple",
    "state": "available",
    "tags": {},
    "virtualization_type": "hvm"
  },
  {
    "ami_id": "ami-07386fce01632d7a5",
    "architecture": "x86_64",
    "description": "Amazon Linux 2023 AMI 2023.11.20260427.1 x86_64 Minimal HVM kernel-6.1",
    "hypervisor": "xen",
    "image_type": "machine",
    "name": "al2023-ami-minimal-2023.11.20260427.1-kernel-6.1-x86_64",
    "owner_id": "137112412989",
    "platform": null,
    "public": true,
    "root_device_name": "/dev/xvda",
    "root_device_type": "ebs",
    "sriov": "simple",
    "state": "available",
    "tags": {},
    "virtualization_type": "hvm"
  },
  {
    "ami_id": "ami-08ddea64886b9150e",
    "architecture": "x86_64",
    "description": "Amazon Linux 2023 AMI 2023.11.20260427.1 x86_64 HVM kernel-6.1",
    "hypervisor": "xen",
    "image_type": "machine",
    "name": "al2023-ami-2023.11.20260427.1-kernel-6.1-x86_64",
    "owner_id": "137112412989",
    "platform": null,
    "public": true,
    "root_device_name": "/dev/xvda",
    "root_device_type": "ebs",
    "sriov": "simple",
    "state": "available",
    "tags": {},
    "virtualization_type": "hvm"
  },
  {
    "ami_id": "ami-04b8f580c1301b47a",
    "architecture": "x86_64",
    "description": "Amazon Linux 2 Kernel 5.10 AMI 2.0.20260427.1 x86_64 Minimal HVM gp2",
    "hypervisor": "xen",
    "image_type": "machine",
    "name": "amzn2-ami-minimal-kernel-5.10-hvm-2.0.20260427.1-x86_64-gp2",
    "owner_id": "137112412989",
    "platform": null,
    "public": true,
    "root_device_name": "/dev/xvda",
    "root_device_type": "ebs",
    "sriov": "simple",
    "state": "available",
    "tags": {},
    "virtualization_type": "hvm"
  },
  {
    "ami_id": "ami-02af97328e5ae4372",
    "architecture": "x86_64",
    "description": "Amazon Linux 2 AMI 2.0.20260427.1 x86_64 HVM gp2",
    "hypervisor": "xen",
    "image_type": "machine",
    "name": "amzn2-ami-hvm-2.0.20260427.1-x86_64-gp2",
    "owner_id": "137112412989",
    "platform": null,
    "public": true,
    "root_device_name": "/dev/xvda",
    "root_device_type": "ebs",
    "sriov": "simple",
    "state": "available",
    "tags": {},
    "virtualization_type": "hvm"
  },
  {
    "ami_id": "ami-06b70aca4f444e3bd",
    "architecture": "x86_64",
    "description": "Amazon Linux AMI 2018.03.0.20231218.0 x86_64 HVM gp2",
    "hypervisor": "xen",
    "image_type": "machine",
    "name": "amzn-ami-hvm-2018.03.0.20231218.0-x86_64-gp2",
    "owner_id": "137112412989",
    "platform": null,
    "public": true,
    "root_device_name": "/dev/xvda",
    "root_device_type": "ebs",
    "sriov": "simple",
    "state": "available",
    "tags": {},
    "virtualization_type": "hvm"
  },
  {
    "ami_id": "ami-0b0c5909734c34ebd",
    "architecture": "x86_64",
    "description": "Amazon Linux 2023 AMI 2023.11.20260427.1 x86_64 Minimal HVM kernel-6.12",
    "hypervisor": "xen",
    "image_type": "machine",
    "name": "al2023-ami-minimal-2023.11.20260427.1-kernel-6.12-x86_64",
    "owner_id": "137112412989",
    "platform": null,
    "public": true,
    "root_device_name": "/dev/xvda",
    "root_device_type": "ebs",
    "sriov": "simple",
    "state": "available",
    "tags": {},
    "virtualization_type": "hvm"
  },
  {
    "ami_id": "ami-0040b957bd206aae2",
    "architecture": "x86_64",
    "description": "Amazon Linux 2023 AMI 2023.11.20260427.1 x86_64 Minimal HVM kernel-6.18",
    "hypervisor": "xen",
    "image_type": "machine",
    "name": "al2023-ami-minimal-2023.11.20260427.1-kernel-6.18-x86_64",
    "owner_id": "137112412989",
    "platform": null,
    "public": true,
    "root_device_name": "/dev/xvda",
    "root_device_type": "ebs",
    "sriov": "simple",
    "state": "available",
    "tags": {},
    "virtualization_type": "hvm"
  },
  {
    "ami_id": "ami-038d56cc345bc000e",
    "architecture": "x86_64",
    "description": "Amazon Linux 2 AMI 2.0.20260427.1 x86_64 HVM ebs",
    "hypervisor": "xen",
    "image_type": "machine",
    "name": "amzn2-ami-hvm-2.0.20260427.1-x86_64-ebs",
    "owner_id": "137112412989",
    "platform": null,
    "public": true,
    "root_device_name": "/dev/xvda",
    "root_device_type": "ebs",
    "sriov": "simple",
    "state": "available",
    "tags": {},
    "virtualization_type": "hvm"
  },
  {
    "ami_id": "ami-092f677b8e61a2117",
    "architecture": "arm64",
    "description": "Amazon Linux 2023 AMI 2023.11.20260427.1 arm64 HVM kernel-6.18",
    "hypervisor": "xen",
    "image_type": "machine",
    "name": "al2023-ami-2023.11.20260427.1-kernel-6.18-arm64",
    "owner_id": "137112412989",
    "platform": null,
    "public": true,
    "root_device_name": "/dev/xvda",
    "root_device_type": "ebs",
    "sriov": "simple",
    "state": "available",
    "tags": {},
    "virtualization_type": "hvm"
  },
  {
    "ami_id": "ami-0bbb07411c74cf5dd",
    "architecture": "x86_64",
    "description": "Amazon Linux 2 Kernel 5.10 AMI 2.0.20260427.1 x86_64 HVM ebs",
    "hypervisor": "xen",
    "image_type": "machine",
    "name": "amzn2-ami-kernel-5.10-hvm-2.0.20260427.1-x86_64-ebs",
    "owner_id": "137112412989",
    "platform": null,
    "public": true,
    "root_device_name": "/dev/xvda",
    "root_device_type": "ebs",
    "sriov": "simple",
    "state": "available",
    "tags": {},
    "virtualization_type": "hvm"
  },
  {
    "ami_id": "ami-0bd6b8f4237f825b1",
    "architecture": "x86_64",
    "description": "Amazon Linux 2 Kernel 5.10 AMI 2.0.20260427.1 x86_64 HVM gp2",
    "hypervisor": "xen",
    "image_type": "machine",
    "name": "amzn2-ami-kernel-5.10-hvm-2.0.20260427.1-x86_64-gp2",
    "owner_id": "137112412989",
    "platform": null,
    "public": true,
    "root_device_name": "/dev/xvda",
    "root_device_type": "ebs",
    "sriov": "simple",
    "state": "available",
    "tags": {},
    "virtualization_type": "hvm"
  },
  {
    "ami_id": "ami-0cf34810fcd14a002",
    "architecture": "arm64",
    "description": "Amazon Linux 2023 AMI 2023.11.20260427.1 arm64 Minimal HVM kernel-6.18",
    "hypervisor": "xen",
    "image_type": "machine",
    "name": "al2023-ami-minimal-2023.11.20260427.1-kernel-6.18-arm64",
    "owner_id": "137112412989",
    "platform": null,
    "public": true,
    "root_device_name": "/dev/xvda",
    "root_device_type": "ebs",
    "sriov": "simple",
    "state": "available",
    "tags": {},
    "virtualization_type": "hvm"
  },
  {
    "ami_id": "ami-03a2093e132f2e6cf",
    "architecture": "x86_64",
    "description": "Amazon Linux AMI 2018.03.0.20231218.0 x86_64 HVM ebs",
    "hypervisor": "xen",
    "image_type": "machine",
    "name": "amzn-ami-hvm-2018.03.0.20231218.0-x86_64-ebs",
    "owner_id": "137112412989",
    "platform": null,
    "public": true,
    "root_device_name": "/dev/xvda",
    "root_device_type": "ebs",
    "sriov": "simple",
    "state": "available",
    "tags": {},
    "virtualization_type": "hvm"
  },
  {
    "ami_id": "ami-0cadc99e829e2b9a8",
    "architecture": "arm64",
    "description": "Amazon Linux 2 LTS Arm64 Kernel 5.10 AMI 2.0.20260427.1 arm64 Minimal HVM gp2",
    "hypervisor": "xen",
    "image_type": "machine",
    "name": "amzn2-ami-minimal-kernel-5.10-hvm-2.0.20260427.1-arm64-gp2",
    "owner_id": "137112412989",
    "platform": null,
    "public": true,
    "root_device_name": "/dev/xvda",
    "root_device_type": "ebs",
    "sriov": "simple",
    "state": "available",
    "tags": {},
    "virtualization_type": "hvm"
  },
  {
    "ami_id": "ami-0641e352143d1dfbf",
    "architecture": "x86_64",
    "description": "Amazon Linux 2023 AMI 2023.11.20260427.1 x86_64 HVM kernel-6.12",
    "hypervisor": "xen",
    "image_type": "machine",
    "name": "al2023-ami-2023.11.20260427.1-kernel-6.12-x86_64",
    "owner_id": "137112412989",
    "platform": null,
    "public": true,
    "root_device_name": "/dev/xvda",
    "root_device_type": "ebs",
    "sriov": "simple",
    "state": "available",
    "tags": {},
    "virtualization_type": "hvm"
  },
  {
    "ami_id": "ami-01794bcd54dc0f0df",
    "architecture": "x86_64",
    "description": "Amazon Linux 2 AMI 2.0.20260427.1 x86_64 Minimal HVM ebs",
    "hypervisor": "xen",
    "image_type": "machine",
    "name": "amzn2-ami-minimal-hvm-2.0.20260427.1-x86_64-ebs",
    "owner_id": "137112412989",
    "platform": null,
    "public": true,
    "root_device_name": "/dev/xvda",
    "root_device_type": "ebs",
    "sriov": "simple",
    "state": "available",
    "tags": {},
    "virtualization_type": "hvm"
  },
  {
    "ami_id": "ami-0664d09b2f57fec69",
    "architecture": "arm64",
    "description": "Amazon Linux 2 LTS Arm64 AMI 2.0.20260427.1 arm64 Minimal HVM ebs",
    "hypervisor": "xen",
    "image_type": "machine",
    "name": "amzn2-ami-minimal-hvm-2.0.20260427.1-arm64-ebs",
    "owner_id": "137112412989",
    "platform": null,
    "public": true,
    "root_device_name": "/dev/xvda",
    "root_device_type": "ebs",
    "sriov": "simple",
    "state": "available",
    "tags": {},
    "virtualization_type": "hvm"
  },
  {
    "ami_id": "ami-0fa36f158af0b1a67",
    "architecture": "arm64",
    "description": "Amazon Linux 2023 AMI 2023.11.20260427.1 arm64 Minimal HVM kernel-6.12",
    "hypervisor": "xen",
    "image_type": "machine",
    "name": "al2023-ami-minimal-2023.11.20260427.1-kernel-6.12-arm64",
    "owner_id": "137112412989",
    "platform": null,
    "public": true,
    "root_device_name": "/dev/xvda",
    "root_device_type": "ebs",
    "sriov": "simple",
    "state": "available",
    "tags": {},
    "virtualization_type": "hvm"
  },
  {
    "ami_id": "ami-06fbcc76c02e8163f",
    "architecture": "arm64",
    "description": "Amazon Linux 2023 AMI 2023.11.20260427.1 arm64 HVM kernel-6.1",
    "hypervisor": "xen",
    "image_type": "machine",
    "name": "al2023-ami-2023.11.20260427.1-kernel-6.1-arm64",
    "owner_id": "137112412989",
    "platform": null,
    "public": true,
    "root_device_name": "/dev/xvda",
    "root_device_type": "ebs",
    "sriov": "simple",
    "state": "available",
    "tags": {},
    "virtualization_type": "hvm"
  },
  {
    "ami_id": "ami-0778d86b31b1d449a",
    "architecture": "arm64",
    "description": "Amazon Linux 2023 AMI 2023.11.20260427.1 arm64 Minimal HVM kernel-6.1",
    "hypervisor": "xen",
    "image_type": "machine",
    "name": "al2023-ami-minimal-2023.11.20260427.1-kernel-6.1-arm64",
    "owner_id": "137112412989",
    "platform": null,
    "public": true,
    "root_device_name": "/dev/xvda",
    "root_device_type": "ebs",
    "sriov": "simple",
    "state": "available",
    "tags": {},
    "virtualization_type": "hvm"
  }
]