[
  {
    "ami_id": "ami-0d09a0250ffd7c55e",
    "architecture": "x86_64",
    "description": "Amazon Linux 2 AMI 2.0.20250527.1 x86_64 Minimal HVM ebs",
    "hypervisor": "xen",
    "image_type": "machine",
    "name": "amzn2-ami-minimal-hvm-2.0.20250527.1-x86_64-ebs",
    "owner_id": "541802698383",
    "platform": null,
    "public": true,
    "root_device_name": "/dev/xvda",
    "root_device_type": "ebs",
    "sriov": "simple",
    "state": "available",
    "tags": {},
    "virtualization_type": "hvm"
  },
  {
    "ami_id": "ami-05a58036c69462295",
    "architecture": "arm64",
    "description": "Amazon Linux 2023 AMI 2023.7.20250512.0 arm64 HVM kernel-6.12",
    "hypervisor": "xen",
    "image_type": "machine",
    "name": "al2023-ami-2023.7.20250512.0-kernel-6.12-arm64",
    "owner_id": "541802698383",
    "platform": null,
    "public": true,
    "root_device_name": "/dev/xvda",
    "root_device_type": "ebs",
    "sriov": "simple",
    "state": "available",
    "tags": {},
    "virtualization_type": "hvm"
  },
  {
    "ami_id": "ami-0f71e8564029d64c8",
    "architecture": "arm64",
    "description": "Amazon Linux 2023 AMI 2023.7.20250512.0 arm64 Minimal HVM kernel-6.1",
    "hypervisor": "xen",
    "image_type": "machine",
    "name": "al2023-ami-minimal-2023.7.20250512.0-kernel-6.1-arm64",
    "owner_id": "541802698383",
    "platform": null,
    "public": true,
    "root_device_name": "/dev/xvda",
    "root_device_type": "ebs",
    "sriov": "simple",
    "state": "available",
    "tags": {},
    "virtualization_type": "hvm"
  },
  {
    "ami_id": "ami-0ddfca74eb6831260",
    "architecture": "x86_64",
    "description": "Amazon Linux 2023 AMI 2023.7.20250512.0 x86_64 Minimal HVM kernel-6.1",
    "hypervisor": "xen",
    "image_type": "machine",
    "name": "al2023-ami-minimal-2023.7.20250512.0-kernel-6.1-x86_64",
    "owner_id": "541802698383",
    "platform": null,
    "public": true,
    "root_device_name": "/dev/xvda",
    "root_device_type": "ebs",
    "sriov": "simple",
    "state": "available",
    "tags": {},
    "virtualization_type": "hvm"
  },
  {
    "ami_id": "ami-0178175c071ffc9e8",
    "architecture": "x86_64",
    "description": "Amazon Linux 2023 AMI 2023.7.20250512.0 x86_64 HVM kernel-6.1",
    "hypervisor": "xen",
    "image_type": "machine",
    "name": "al2023-ami-2023.7.20250512.0-kernel-6.1-x86_64",
    "owner_id": "541802698383",
    "platform": null,
    "public": true,
    "root_device_name": "/dev/xvda",
    "root_device_type": "ebs",
    "sriov": "simple",
    "state": "available",
    "tags": {},
    "virtualization_type": "hvm"
  },
  {
    "ami_id": "ami-03f02d7001cc9fd97",
    "architecture": "x86_64",
    "description": "Amazon Linux AMI 2018.03.0.20231218.0 x86_64 HVM ebs",
    "hypervisor": "xen",
    "image_type": "machine",
    "name": "amzn-ami-hvm-2018.03.0.20231218.0-x86_64-ebs",
    "owner_id": "541802698383",
    "platform": null,
    "public": true,
    "root_device_name": "/dev/xvda",
    "root_device_type": "ebs",
    "sriov": "simple",
    "state": "available",
    "tags": {},
    "virtualization_type": "hvm"
  },
  {
    "ami_id": "ami-07dbe6e5a34ce6842",
    "architecture": "x86_64",
    "description": "Amazon Linux AMI 2018.03.0.20231218.0 x86_64 HVM gp2",
    "hypervisor": "xen",
    "image_type": "machine",
    "name": "amzn-ami-hvm-2018.03.0.20231218.0-x86_64-gp2",
    "owner_id": "541802698383",
    "platform": null,
    "public": true,
    "root_device_name": "/dev/xvda",
    "root_device_type": "ebs",
    "sriov": "simple",
    "state": "available",
    "tags": {},
    "virtualization_type": "hvm"
  },
  {
    "ami_id": "ami-047104ca70a255ea3",
    "architecture": "x86_64",
    "description": "Amazon Linux 2023 AMI 2023.7.20250512.0 x86_64 HVM kernel-6.12",
    "hypervisor": "xen",
    "image_type": "machine",
    "name": "al2023-ami-2023.7.20250512.0-kernel-6.12-x86_64",
    "owner_id": "541802698383",
    "platform": null,
    "public": true,
    "root_device_name": "/dev/xvda",
    "root_device_type": "ebs",
    "sriov": "simple",
    "state": "available",
    "tags": {},
    "virtualization_type": "hvm"
  },
  {
    "ami_id": "ami-0ed4ec15ffd919b73",
    "architecture": "arm64",
    "description": "Amazon Linux 2023 AMI 2023.7.20250512.0 arm64 HVM kernel-6.1",
    "hypervisor": "xen",
    "image_type": "machine",
    "name": "al2023-ami-2023.7.20250512.0-kernel-6.1-arm64",
    "owner_id": "541802698383",
    "platform": null,
    "public": true,
    "root_device_name": "/dev/xvda",
    "root_device_type": "ebs",
    "sriov": "simple",
    "state": "available",
    "tags": {},
    "virtualization_type": "hvm"
  },
  {
    "ami_id": "ami-089d2fe47624157bb",
    "architecture": "x86_64",
    "description": "Amazon Linux 2 AMI 2.0.20250527.1 x86_64 HVM gp2",
    "hypervisor": "xen",
    "image_type": "machine",
    "name": "amzn2-ami-hvm-2.0.20250527.1-x86_64-gp2",
    "owner_id": "541802698383",
    "platform": null,
    "public": true,
    "root_device_name": "/dev/xvda",
    "root_device_type": "ebs",
    "sriov": "simple",
    "state": "available",
    "tags": {},
    "virtualization_type": "hvm"
  },
  {
    "ami_id": "ami-0107ce2dea78f5132",
    "architecture": "x86_64",
    "description": "Amazon Linux 2 Kernel 5.10 AMI 2.0.20250527.1 x86_64 HVM gp2",
    "hypervisor": "xen",
    "image_type": "machine",
    "name": "amzn2-ami-kernel-5.10-hvm-2.0.20250527.1-x86_64-gp2",
    "owner_id": "541802698383",
    "platform": null,
    "public": true,
    "root_device_name": "/dev/xvda",
    "root_device_type": "ebs",
    "sriov": "simple",
    "state": "available",
    "tags": {},
    "virtualization_type": "hvm"
  },
  {
    "ami_id": "ami-04b706bd0f1ab003e",
    "architecture": "arm64",
    "description": "Amazon Linux 2023 AMI 2023.7.20250512.0 arm64 Minimal HVM kernel-6.12",
    "hypervisor": "xen",
    "image_type": "machine",
    "name": "al2023-ami-minimal-2023.7.20250512.0-kernel-6.12-arm64",
    "owner_id": "541802698383",
    "platform": null,
    "public": true,
    "root_device_name": "/dev/xvda",
    "root_device_type": "ebs",
    "sriov": "simple",
    "state": "available",
    "tags": {},
    "virtualization_type": "hvm"
  },
  {
    "ami_id": "ami-08778543d8ec3d0ed",
    "architecture": "x86_64",
    "description": "Amazon Linux 2 AMI 2.0.20250527.1 x86_64 HVM ebs",
    "hypervisor": "xen",
    "image_type": "machine",
    "name": "amzn2-ami-hvm-2.0.20250527.1-x86_64-ebs",
    "owner_id": "541802698383",
    "platform": null,
    "public": true,
    "root_device_name": "/dev/xvda",
    "root_device_type": "ebs",
    "sriov": "simple",
    "state": "available",
    "tags": {},
    "virtualization_type": "hvm"
  },
  {
    "ami_id": "ami-0bd829390f78c69da",
    "architecture": "arm64",
    "description": "Amazon Linux 2 LTS Arm64 AMI 2.0.20250527.1 arm64 Minimal HVM ebs",
    "hypervisor": "xen",
    "image_type": "machine",
    "name": "amzn2-ami-minimal-hvm-2.0.20250527.1-arm64-ebs",
    "owner_id": "541802698383",
    "platform": null,
    "public": true,
    "root_device_name": "/dev/xvda",
    "root_device_type": "ebs",
    "sriov": "simple",
    "state": "available",
    "tags": {},
    "virtualization_type": "hvm"
  },
  {
    "ami_id": "ami-0a81113adb45696f8",
    "architecture": "x86_64",
    "description": "Amazon Linux 2 Kernel 5.10 AMI 2.0.20250527.1 x86_64 HVM ebs",
    "hypervisor": "xen",
    "image_type": "machine",
    "name": "amzn2-ami-kernel-5.10-hvm-2.0.20250527.1-x86_64-ebs",
    "owner_id": "541802698383",
    "platform": null,
    "public": true,
    "root_device_name": "/dev/xvda",
    "root_device_type": "ebs",
    "sriov": "simple",
    "state": "available",
    "tags": {},
    "virtualization_type": "hvm"
  },
  {
    "ami_id": "ami-056f2f19264275049",
    "architecture": "x86_64",
    "description": "Amazon Linux 2023 AMI 2023.7.20250512.0 x86_64 Minimal HVM kernel-6.12",
    "hypervisor": "xen",
    "image_type": "machine",
    "name": "al2023-ami-minimal-2023.7.20250512.0-kernel-6.12-x86_64",
    "owner_id": "541802698383",
    "platform": null,
    "public": true,
    "root_device_name": "/dev/xvda",
    "root_device_type": "ebs",
    "sriov": "simple",
    "state": "available",
    "tags": {},
    "virtualization_type": "hvm"
  },
  {
    "ami_id": "ami-0b37599d252fa0243",
    "architecture": "arm64",
    "description": "Amazon Linux 2 LTS Arm64 AMI 2.0.20250527.1 arm64 HVM gp2",
    "hypervisor": "xen",
    "image_type": "machine",
    "name": "amzn2-ami-hvm-2.0.20250527.1-arm64-gp2",
    "owner_id": "541802698383",
    "platform": null,
    "public": true,
    "root_device_name": "/dev/xvda",
    "root_device_type": "ebs",
    "sriov": "simple",
    "state": "available",
    "tags": {},
    "virtualization_type": "hvm"
  },
  {
    "ami_id": "ami-07efec4358a395eae",
    "architecture": "arm64",
    "description": "Amazon Linux 2 LTS Arm64 Kernel 5.10 AMI 2.0.20250527.1 arm64 HVM gp2",
    "hypervisor": "xen",
    "image_type": "machine",
    "name": "amzn2-ami-kernel-5.10-hvm-2.0.20250527.1-arm64-gp2",
    "owner_id": "541802698383",
    "platform": null,
    "public": true,
    "root_device_name": "/dev/xvda",
    "root_device_type": "ebs",
    "sriov": "simple",
    "state": "available",
    "tags": {},
    "virtualization_type": "hvm"
  }
]