[
  {
    "ami_id": "ami-040f51140da8eed09",
    "architecture": "x86_64",
    "description": "Amazon Linux 2023 AMI 2023.9.20251117.1 x86_64 Minimal HVM kernel-6.12",
    "hypervisor": "xen",
    "image_type": "machine",
    "name": "al2023-ami-minimal-2023.9.20251117.1-kernel-6.12-x86_64",
    "owner_id": "541802698383",
    "platform": null,
    "public": true,
    "root_device_name": "/dev/xvda",
    "root_device_type": "ebs",
    "sriov": "simple",
    "state": "available",
    "tags": {},
    "virtualization_type": "hvm"
  },
  {
    "ami_id": "ami-05d7ad72102b38474",
    "architecture": "x86_64",
    "description": "Amazon Linux 2 Kernel 5.10 AMI 2.0.20251121.0 x86_64 Minimal HVM gp2",
    "hypervisor": "xen",
    "image_type": "machine",
    "name": "amzn2-ami-minimal-kernel-5.10-hvm-2.0.20251121.0-x86_64-gp2",
    "owner_id": "541802698383",
    "platform": null,
    "public": true,
    "root_device_name": "/dev/xvda",
    "root_device_type": "ebs",
    "sriov": "simple",
    "state": "available",
    "tags": {},
    "virtualization_type": "hvm"
  },
  {
    "ami_id": "ami-04b031bdd25f7f062",
    "architecture": "x86_64",
    "description": "Amazon Linux 2023 AMI 2023.9.20251117.1 x86_64 HVM kernel-6.12",
    "hypervisor": "xen",
    "image_type": "machine",
    "name": "al2023-ami-2023.9.20251117.1-kernel-6.12-x86_64",
    "owner_id": "541802698383",
    "platform": null,
    "public": true,
    "root_device_name": "/dev/xvda",
    "root_device_type": "ebs",
    "sriov": "simple",
    "state": "available",
    "tags": {},
    "virtualization_type": "hvm"
  },
  {
    "ami_id": "ami-05e66df2bafcb7dea",
    "architecture": "x86_64",
    "description": "Amazon Linux 2023 AMI 2023.9.20251117.1 x86_64 HVM kernel-6.1",
    "hypervisor": "xen",
    "image_type": "machine",
    "name": "al2023-ami-2023.9.20251117.1-kernel-6.1-x86_64",
    "owner_id": "541802698383",
    "platform": null,
    "public": true,
    "root_device_name": "/dev/xvda",
    "root_device_type": "ebs",
    "sriov": "simple",
    "state": "available",
    "tags": {},
    "virtualization_type": "hvm"
  },
  {
    "ami_id": "ami-02267faa759886e83",
    "architecture": "arm64",
    "description": "Amazon Linux 2023 AMI 2023.9.20251117.1 arm64 Minimal HVM kernel-6.12",
    "hypervisor": "xen",
    "image_type": "machine",
    "name": "al2023-ami-minimal-2023.9.20251117.1-kernel-6.12-arm64",
    "owner_id": "541802698383",
    "platform": null,
    "public": true,
    "root_device_name": "/dev/xvda",
    "root_device_type": "ebs",
    "sriov": "simple",
    "state": "available",
    "tags": {},
    "virtualization_type": "hvm"
  },
  {
    "ami_id": "ami-024f3cb85657ab82c",
    "architecture": "arm64",
    "description": "Amazon Linux 2 LTS Arm64 AMI 2.0.20251121.0 arm64 Minimal HVM ebs",
    "hypervisor": "xen",
    "image_type": "machine",
    "name": "amzn2-ami-minimal-hvm-2.0.20251121.0-arm64-ebs",
    "owner_id": "541802698383",
    "platform": null,
    "public": true,
    "root_device_name": "/dev/xvda",
    "root_device_type": "ebs",
    "sriov": "simple",
    "state": "available",
    "tags": {},
    "virtualization_type": "hvm"
  },
  {
    "ami_id": "ami-0d5275409ba7c580c",
    "architecture": "arm64",
    "description": "Amazon Linux 2023 AMI 2023.9.20251117.1 arm64 HVM kernel-6.12",
    "hypervisor": "xen",
    "image_type": "machine",
    "name": "al2023-ami-2023.9.20251117.1-kernel-6.12-arm64",
    "owner_id": "541802698383",
    "platform": null,
    "public": true,
    "root_device_name": "/dev/xvda",
    "root_device_type": "ebs",
    "sriov": "simple",
    "state": "available",
    "tags": {},
    "virtualization_type": "hvm"
  },
  {
    "ami_id": "ami-051a94e493aab2e41",
    "architecture": "arm64",
    "description": "Amazon Linux 2 LTS Arm64 Kernel 5.10 AMI 2.0.20251121.0 arm64 HVM gp2",
    "hypervisor": "xen",
    "image_type": "machine",
    "name": "amzn2-ami-kernel-5.10-hvm-2.0.20251121.0-arm64-gp2",
    "owner_id": "541802698383",
    "platform": null,
    "public": true,
    "root_device_name": "/dev/xvda",
    "root_device_type": "ebs",
    "sriov": "simple",
    "state": "available",
    "tags": {},
    "virtualization_type": "hvm"
  },
  {
    "ami_id": "ami-08550ec4fde127f5a",
    "architecture": "x86_64",
    "description": "Amazon Linux 2 AMI 2.0.20251121.0 x86_64 HVM ebs",
    "hypervisor": "xen",
    "image_type": "machine",
    "name": "amzn2-ami-hvm-2.0.20251121.0-x86_64-ebs",
    "owner_id": "541802698383",
    "platform": null,
    "public": true,
    "root_device_name": "/dev/xvda",
    "root_device_type": "ebs",
    "sriov": "simple",
    "state": "available",
    "tags": {},
    "virtualization_type": "hvm"
  },
  {
    "ami_id": "ami-0d90f860e9d3b1c73",
    "architecture": "arm64",
    "description": "Amazon Linux 2023 AMI 2023.9.20251117.1 arm64 HVM kernel-6.1",
    "hypervisor": "xen",
    "image_type": "machine",
    "name": "al2023-ami-2023.9.20251117.1-kernel-6.1-arm64",
    "owner_id": "541802698383",
    "platform": null,
    "public": true,
    "root_device_name": "/dev/xvda",
    "root_device_type": "ebs",
    "sriov": "simple",
    "state": "available",
    "tags": {},
    "virtualization_type": "hvm"
  },
  {
    "ami_id": "ami-0e969daef6c123f58",
    "architecture": "x86_64",
    "description": "Amazon Linux 2 Kernel 5.10 AMI 2.0.20251121.0 x86_64 HVM gp2",
    "hypervisor": "xen",
    "image_type": "machine",
    "name": "amzn2-ami-kernel-5.10-hvm-2.0.20251121.0-x86_64-gp2",
    "owner_id": "541802698383",
    "platform": null,
    "public": true,
    "root_device_name": "/dev/xvda",
    "root_device_type": "ebs",
    "sriov": "simple",
    "state": "available",
    "tags": {},
    "virtualization_type": "hvm"
  },
  {
    "ami_id": "ami-053ede27496234115",
    "architecture": "x86_64",
    "description": "Amazon Linux 2023 AMI 2023.9.20251117.1 x86_64 Minimal HVM kernel-6.1",
    "hypervisor": "xen",
    "image_type": "machine",
    "name": "al2023-ami-minimal-2023.9.20251117.1-kernel-6.1-x86_64",
    "owner_id": "541802698383",
    "platform": null,
    "public": true,
    "root_device_name": "/dev/xvda",
    "root_device_type": "ebs",
    "sriov": "simple",
    "state": "available",
    "tags": {},
    "virtualization_type": "hvm"
  },
  {
    "ami_id": "ami-0f13362a23b914615",
    "architecture": "x86_64",
    "description": "Amazon Linux 2 AMI 2.0.20251121.0 x86_64 HVM gp2",
    "hypervisor": "xen",
    "image_type": "machine",
    "name": "amzn2-ami-hvm-2.0.20251121.0-x86_64-gp2",
    "owner_id": "541802698383",
    "platform": null,
    "public": true,
    "root_device_name": "/dev/xvda",
    "root_device_type": "ebs",
    "sriov": "simple",
    "state": "available",
    "tags": {},
    "virtualization_type": "hvm"
  },
  {
    "ami_id": "ami-0ac7398ffc55d8732",
    "architecture": "arm64",
    "description": "Amazon Linux 2 LTS Arm64 AMI 2.0.20251121.0 arm64 HVM gp2",
    "hypervisor": "xen",
    "image_type": "machine",
    "name": "amzn2-ami-hvm-2.0.20251121.0-arm64-gp2",
    "owner_id": "541802698383",
    "platform": null,
    "public": true,
    "root_device_name": "/dev/xvda",
    "root_device_type": "ebs",
    "sriov": "simple",
    "state": "available",
    "tags": {},
    "virtualization_type": "hvm"
  },
  {
    "ami_id": "ami-07dbe6e5a34ce6842",
    "architecture": "x86_64",
    "description": "Amazon Linux AMI 2018.03.0.20231218.0 x86_64 HVM gp2",
    "hypervisor": "xen",
    "image_type": "machine",
    "name": "amzn-ami-hvm-2018.03.0.20231218.0-x86_64-gp2",
    "owner_id": "541802698383",
    "platform": null,
    "public": true,
    "root_device_name": "/dev/xvda",
    "root_device_type": "ebs",
    "sriov": "simple",
    "state": "available",
    "tags": {},
    "virtualization_type": "hvm"
  },
  {
    "ami_id": "ami-047a618dc5f89a34d",
    "architecture": "x86_64",
    "description": "Amazon Linux 2 Kernel 5.10 AMI 2.0.20251121.0 x86_64 HVM ebs",
    "hypervisor": "xen",
    "image_type": "machine",
    "name": "amzn2-ami-kernel-5.10-hvm-2.0.20251121.0-x86_64-ebs",
    "owner_id": "541802698383",
    "platform": null,
    "public": true,
    "root_device_name": "/dev/xvda",
    "root_device_type": "ebs",
    "sriov": "simple",
    "state": "available",
    "tags": {},
    "virtualization_type": "hvm"
  },
  {
    "ami_id": "ami-0118ff3e8b84afffc",
    "architecture": "arm64",
    "description": "Amazon Linux 2 LTS Arm64 Kernel 5.10 AMI 2.0.20251121.0 arm64 Minimal HVM gp2",
    "hypervisor": "xen",
    "image_type": "machine",
    "name": "amzn2-ami-minimal-kernel-5.10-hvm-2.0.20251121.0-arm64-gp2",
    "owner_id": "541802698383",
    "platform": null,
    "public": true,
    "root_device_name": "/dev/xvda",
    "root_device_type": "ebs",
    "sriov": "simple",
    "state": "available",
    "tags": {},
    "virtualization_type": "hvm"
  },
  {
    "ami_id": "ami-097ae8389fa5768a1",
    "architecture": "x86_64",
    "description": "Amazon Linux 2 AMI 2.0.20251121.0 x86_64 Minimal HVM ebs",
    "hypervisor": "xen",
    "image_type": "machine",
    "name": "amzn2-ami-minimal-hvm-2.0.20251121.0-x86_64-ebs",
    "owner_id": "541802698383",
    "platform": null,
    "public": true,
    "root_device_name": "/dev/xvda",
    "root_device_type": "ebs",
    "sriov": "simple",
    "state": "available",
    "tags": {},
    "virtualization_type": "hvm"
  },
  {
    "ami_id": "ami-0e385e0c001834850",
    "architecture": "arm64",
    "description": "Amazon Linux 2023 AMI 2023.9.20251117.1 arm64 Minimal HVM kernel-6.1",
    "hypervisor": "xen",
    "image_type": "machine",
    "name": "al2023-ami-minimal-2023.9.20251117.1-kernel-6.1-arm64",
    "owner_id": "541802698383",
    "platform": null,
    "public": true,
    "root_device_name": "/dev/xvda",
    "root_device_type": "ebs",
    "sriov": "simple",
    "state": "available",
    "tags": {},
    "virtualization_type": "hvm"
  }
]