[{"InstanceType": "r5.16xlarge", "Location": "euw3-az3", "LocationType": "availability-zone-id"}, {"InstanceType": "i3.large", "Location": "euw3-az2", "LocationType": "availability-zone-id"}, {"InstanceType": "m5ad.24xlarge", "Location": "euw3-az1", "LocationType": "availability-zone-id"}, {"InstanceType": "m5a.xlarge", "Location": "euw3-az1", "LocationType": "availability-zone-id"}, {"InstanceType": "m5d.large", "Location": "euw3-az3", "LocationType": "availability-zone-id"}, {"InstanceType": "r5ad.4xlarge", "Location": "euw3-az3", "LocationType": "availability-zone-id"}, {"InstanceType": "m5a.8xlarge", "Location": "euw3-az2", "LocationType": "availability-zone-id"}, {"InstanceType": "t2.medium", "Location": "euw3-az1", "LocationType": "availability-zone-id"}, {"InstanceType": "r5d.4xlarge", "Location": "euw3-az2", "LocationType": "availability-zone-id"}, {"InstanceType": "r5ad.12xlarge", "Location": "euw3-az1", "LocationType": "availability-zone-id"}, {"InstanceType": "d2.2xlarge", "Location": "euw3-az2", "LocationType": "availability-zone-id"}, {"InstanceType": "m5d.24xlarge", "Location": "euw3-az1", "LocationType": "availability-zone-id"}, {"InstanceType": "r5ad.2xlarge", "Location": "euw3-az2", "LocationType": "availability-zone-id"}, {"InstanceType": "m5d.24xlarge", "Location": "euw3-az2", "LocationType": "availability-zone-id"}, {"InstanceType": "m5d.8xlarge", "Location": "euw3-az3", "LocationType": "availability-zone-id"}, {"InstanceType": "r5a.16xlarge", "Location": "euw3-az3", "LocationType": "availability-zone-id"}, {"InstanceType": "r5a.24xlarge", "Location": "euw3-az3", "LocationType": "availability-zone-id"}, {"InstanceType": "t3.micro", "Location": "euw3-az3", "LocationType": "availability-zone-id"}, {"InstanceType": "m5a.4xlarge", "Location": "euw3-az3", "LocationType": "availability-zone-id"}, {"InstanceType": "m5.metal", "Location": "euw3-az3", "LocationType": "availability-zone-id"}, {"InstanceType": "m5ad.24xlarge", "Location": "euw3-az3", "LocationType": "availability-zone-id"}, {"InstanceType": "i3.8xlarge", "Location": "euw3-az1", "LocationType": "availability-zone-id"}, {"InstanceType": "t2.xlarge", "Location": "euw3-az2", "LocationType": "availability-zone-id"}, {"InstanceType": "m5ad.16xlarge", "Location": "euw3-az2", "LocationType": "availability-zone-id"}, {"InstanceType": "c5.9xlarge", "Location": "euw3-az3", "LocationType": "availability-zone-id"}, {"InstanceType": "i3.2xlarge", "Location": "euw3-az1", "LocationType": "availability-zone-id"}, {"InstanceType": "r5.metal", "Location": "euw3-az3", "LocationType": "availability-zone-id"}, {"InstanceType": "t3a.large", "Location": "euw3-az2", "LocationType": "availability-zone-id"}, {"InstanceType": "m5d.2xlarge", "Location": "euw3-az2", "LocationType": "availability-zone-id"}, {"InstanceType": "c5.4xlarge", "Location": "euw3-az3", "LocationType": "availability-zone-id"}, {"InstanceType": "c5n.18xlarge", "Location": "euw3-az2", "LocationType": "availability-zone-id"}, {"InstanceType": "r5.2xlarge", "Location": "euw3-az1", "LocationType": "availability-zone-id"}, {"InstanceType": "r5d.xlarge", "Location": "euw3-az1", "LocationType": "availability-zone-id"}, {"InstanceType": "r5.12xlarge", "Location": "euw3-az3", "LocationType": "availability-zone-id"}, {"InstanceType": "g4dn.2xlarge", "Location": "euw3-az1", "LocationType": "availability-zone-id"}, {"InstanceType": "i3.16xlarge", "Location": "euw3-az1", "LocationType": "availability-zone-id"}, {"InstanceType": "m5a.xlarge", "Location": "euw3-az2", "LocationType": "availability-zone-id"}, {"InstanceType": "t2.2xlarge", "Location": "euw3-az1", "LocationType": "availability-zone-id"}, {"InstanceType": "d2.8xlarge", "Location": "euw3-az3", "LocationType": "availability-zone-id"}, {"InstanceType": "t2.2xlarge", "Location": "euw3-az2", "LocationType": "availability-zone-id"}, {"InstanceType": "m5ad.16xlarge", "Location": "euw3-az3", "LocationType": "availability-zone-id"}, {"InstanceType": "t3.xlarge", "Location": "euw3-az2", "LocationType": "availability-zone-id"}, {"InstanceType": "m5ad.xlarge", "Location": "euw3-az2", "LocationType": "availability-zone-id"}, {"InstanceType": "c5.metal", "Location": "euw3-az2", "LocationType": "availability-zone-id"}, {"InstanceType": "x1.16xlarge", "Location": "euw3-az1", "LocationType": "availability-zone-id"}, {"InstanceType": "inf1.2xlarge", "Location": "euw3-az1", "LocationType": "availability-zone-id"}, {"InstanceType": "c5n.2xlarge", "Location": "euw3-az3", "LocationType": "availability-zone-id"}, {"InstanceType": "m5ad.16xlarge", "Location": "euw3-az1", "LocationType": "availability-zone-id"}, {"InstanceType": "m5.large", "Location": "euw3-az3", "LocationType": "availability-zone-id"}, {"InstanceType": "r4.2xlarge", "Location": "euw3-az2", "LocationType": "availability-zone-id"}, {"InstanceType": "r5n.12xlarge", "Location": "euw3-az2", "LocationType": "availability-zone-id"}, {"InstanceType": "c5.metal", "Location": "euw3-az3", "LocationType": "availability-zone-id"}, {"InstanceType": "c5a.8xlarge", "Location": "euw3-az3", "LocationType": "availability-zone-id"}, {"InstanceType": "t3a.large", "Location": "euw3-az1", "LocationType": "availability-zone-id"}, {"InstanceType": "r5n.xlarge", "Location": "euw3-az3", "LocationType": "availability-zone-id"}, {"InstanceType": "r5.24xlarge", "Location": "euw3-az2", "LocationType": "availability-zone-id"}, {"InstanceType": "m5d.12xlarge", "Location": "euw3-az1", "LocationType": "availability-zone-id"}, {"InstanceType": "c5d.xlarge", "Location": "euw3-az2", "LocationType": "availability-zone-id"}, {"InstanceType": "c5a.large", "Location": "euw3-az1", "LocationType": "availability-zone-id"}, {"InstanceType": "t3a.small", "Location": "euw3-az3", "LocationType": "availability-zone-id"}, {"InstanceType": "i3en.metal", "Location": "euw3-az3", "LocationType": "availability-zone-id"}, {"InstanceType": "r5d.xlarge", "Location": "euw3-az3", "LocationType": "availability-zone-id"}, {"InstanceType": "r5ad.8xlarge", "Location": "euw3-az2", "LocationType": "availability-zone-id"}, {"InstanceType": "i3en.12xlarge", "Location": "euw3-az3", "LocationType": "availability-zone-id"}, {"InstanceType": "c5.2xlarge", "Location": "euw3-az2", "LocationType": "availability-zone-id"}, {"InstanceType": "i3en.xlarge", "Location": "euw3-az2", "LocationType": "availability-zone-id"}, {"InstanceType": "c5a.12xlarge", "Location": "euw3-az1", "LocationType": "availability-zone-id"}, {"InstanceType": "m5.16xlarge", "Location": "euw3-az2", "LocationType": "availability-zone-id"}, {"InstanceType": "c5a.xlarge", "Location": "euw3-az3", "LocationType": "availability-zone-id"}, {"InstanceType": "i3en.metal", "Location": "euw3-az1", "LocationType": "availability-zone-id"}, {"InstanceType": "m5.8xlarge", "Location": "euw3-az1", "LocationType": "availability-zone-id"}, {"InstanceType": "i3en.6xlarge", "Location": "euw3-az1", "LocationType": "availability-zone-id"}, {"InstanceType": "m5.12xlarge", "Location": "euw3-az3", "LocationType": "availability-zone-id"}, {"InstanceType": "m5ad.12xlarge", "Location": "euw3-az1", "LocationType": "availability-zone-id"}, {"InstanceType": "c5a.8xlarge", "Location": "euw3-az1", "LocationType": "availability-zone-id"}, {"InstanceType": "m5.xlarge", "Location": "euw3-az1", "LocationType": "availability-zone-id"}, {"InstanceType": "c5d.xlarge", "Location": "euw3-az3", "LocationType": "availability-zone-id"}, {"InstanceType": "r5d.2xlarge", "Location": "euw3-az2", "LocationType": "availability-zone-id"}, {"InstanceType": "t3a.micro", "Location": "euw3-az3", "LocationType": "availability-zone-id"}, {"InstanceType": "c5a.24xlarge", "Location": "euw3-az3", "LocationType": "availability-zone-id"}, {"InstanceType": "m5a.24xlarge", "Location": "euw3-az1", "LocationType": "availability-zone-id"}, {"InstanceType": "t3.2xlarge", "Location": "euw3-az1", "LocationType": "availability-zone-id"}, {"InstanceType": "g4dn.metal", "Location": "euw3-az3", "LocationType": "availability-zone-id"}, {"InstanceType": "t3.large", "Location": "euw3-az1", "LocationType": "availability-zone-id"}, {"InstanceType": "t2.nano", "Location": "euw3-az1", "LocationType": "availability-zone-id"}, {"InstanceType": "t3.nano", "Location": "euw3-az1", "LocationType": "availability-zone-id"}, {"InstanceType": "m5.metal", "Location": "euw3-az1", "LocationType": "availability-zone-id"}, {"InstanceType": "r5n.8xlarge", "Location": "euw3-az3", "LocationType": "availability-zone-id"}, {"InstanceType": "c5.12xlarge", "Location": "euw3-az3", "LocationType": "availability-zone-id"}, {"InstanceType": "i3en.metal", "Location": "euw3-az2", "LocationType": "availability-zone-id"}, {"InstanceType": "r5ad.24xlarge", "Location": "euw3-az2", "LocationType": "availability-zone-id"}, {"InstanceType": "g4dn.12xlarge", "Location": "euw3-az1", "LocationType": "availability-zone-id"}, {"InstanceType": "r5.xlarge", "Location": "euw3-az2", "LocationType": "availability-zone-id"}, {"InstanceType": "t3.2xlarge", "Location": "euw3-az3", "LocationType": "availability-zone-id"}, {"InstanceType": "t3a.micro", "Location": "euw3-az1", "LocationType": "availability-zone-id"}, {"InstanceType": "c5n.18xlarge", "Location": "euw3-az3", "LocationType": "availability-zone-id"}, {"InstanceType": "r5ad.2xlarge", "Location": "euw3-az1", "LocationType": "availability-zone-id"}, {"InstanceType": "m5d.metal", "Location": "euw3-az1", "LocationType": "availability-zone-id"}, {"InstanceType": "r5a.12xlarge", "Location": "euw3-az3", "LocationType": "availability-zone-id"}, {"InstanceType": "c5d.2xlarge", "Location": "euw3-az3", "LocationType": "availability-zone-id"}, {"InstanceType": "r5n.12xlarge", "Location": "euw3-az1", "LocationType": "availability-zone-id"}, {"InstanceType": "r4.large", "Location": "euw3-az2", "LocationType": "availability-zone-id"}, {"InstanceType": "t2.small", "Location": "euw3-az3", "LocationType": "availability-zone-id"}, {"InstanceType": "r4.large", "Location": "euw3-az1", "LocationType": "availability-zone-id"}, {"InstanceType": "m5a.2xlarge", "Location": "euw3-az3", "LocationType": "availability-zone-id"}, {"InstanceType": "m5d.4xlarge", "Location": "euw3-az1", "LocationType": "availability-zone-id"}, {"InstanceType": "c5.9xlarge", "Location": "euw3-az1", "LocationType": "availability-zone-id"}, {"InstanceType": "r5n.large", "Location": "euw3-az3", "LocationType": "availability-zone-id"}, {"InstanceType": "r4.16xlarge", "Location": "euw3-az2", "LocationType": "availability-zone-id"}, {"InstanceType": "r5.4xlarge", "Location": "euw3-az3", "LocationType": "availability-zone-id"}, {"InstanceType": "m5d.8xlarge", "Location": "euw3-az2", "LocationType": "availability-zone-id"}, {"InstanceType": "r5d.metal", "Location": "euw3-az2", "LocationType": "availability-zone-id"}, {"InstanceType": "r5ad.large", "Location": "euw3-az1", "LocationType": "availability-zone-id"}, {"InstanceType": "r5n.8xlarge", "Location": "euw3-az1", "LocationType": "availability-zone-id"}, {"InstanceType": "m5a.12xlarge", "Location": "euw3-az2", "LocationType": "availability-zone-id"}, {"InstanceType": "r4.4xlarge", "Location": "euw3-az2", "LocationType": "availability-zone-id"}, {"InstanceType": "g4dn.8xlarge", "Location": "euw3-az3", "LocationType": "availability-zone-id"}, {"InstanceType": "m5a.24xlarge", "Location": "euw3-az2", "LocationType": "availability-zone-id"}, {"InstanceType": "r5d.16xlarge", "Location": "euw3-az3", "LocationType": "availability-zone-id"}, {"InstanceType": "r5a.12xlarge", "Location": "euw3-az2", "LocationType": "availability-zone-id"}, {"InstanceType": "r5d.24xlarge", "Location": "euw3-az1", "LocationType": "availability-zone-id"}, {"InstanceType": "t3a.2xlarge", "Location": "euw3-az2", "LocationType": "availability-zone-id"}, {"InstanceType": "m5a.4xlarge", "Location": "euw3-az2", "LocationType": "availability-zone-id"}, {"InstanceType": "i3.4xlarge", "Location": "euw3-az1", "LocationType": "availability-zone-id"}, {"InstanceType": "r5n.16xlarge", "Location": "euw3-az1", "LocationType": "availability-zone-id"}, {"InstanceType": "r5d.12xlarge", "Location": "euw3-az2", "LocationType": "availability-zone-id"}, {"InstanceType": "r5a.4xlarge", "Location": "euw3-az3", "LocationType": "availability-zone-id"}, {"InstanceType": "t3.micro", "Location": "euw3-az2", "LocationType": "availability-zone-id"}, {"InstanceType": "r5a.2xlarge", "Location": "euw3-az3", "LocationType": "availability-zone-id"}, {"InstanceType": "r4.large", "Location": "euw3-az3", "LocationType": "availability-zone-id"}, {"InstanceType": "d2.2xlarge", "Location": "euw3-az1", "LocationType": "availability-zone-id"}, {"InstanceType": "r5d.8xlarge", "Location": "euw3-az2", "LocationType": "availability-zone-id"}, {"InstanceType": "r5.2xlarge", "Location": "euw3-az2", "LocationType": "availability-zone-id"}, {"InstanceType": "c5a.xlarge", "Location": "euw3-az1", "LocationType": "availability-zone-id"}, {"InstanceType": "m5a.12xlarge", "Location": "euw3-az3", "LocationType": "availability-zone-id"}, {"InstanceType": "g4dn.4xlarge", "Location": "euw3-az2", "LocationType": "availability-zone-id"}, {"InstanceType": "c5a.4xlarge", "Location": "euw3-az1", "LocationType": "availability-zone-id"}, {"InstanceType": "t3.medium", "Location": "euw3-az1", "LocationType": "availability-zone-id"}, {"InstanceType": "x1.32xlarge", "Location": "euw3-az1", "LocationType": "availability-zone-id"}, {"InstanceType": "r5.xlarge", "Location": "euw3-az1", "LocationType": "availability-zone-id"}, {"InstanceType": "t2.xlarge", "Location": "euw3-az3", "LocationType": "availability-zone-id"}, {"InstanceType": "t2.large", "Location": "euw3-az1", "LocationType": "availability-zone-id"}, {"InstanceType": "c5d.large", "Location": "euw3-az1", "LocationType": "availability-zone-id"}, {"InstanceType": "m5d.xlarge", "Location": "euw3-az2", "LocationType": "availability-zone-id"}, {"InstanceType": "c5.2xlarge", "Location": "euw3-az1", "LocationType": "availability-zone-id"}, {"InstanceType": "m5ad.24xlarge", "Location": "euw3-az2", "LocationType": "availability-zone-id"}, {"InstanceType": "x1.16xlarge", "Location": "euw3-az2", "LocationType": "availability-zone-id"}, {"InstanceType": "r5a.2xlarge", "Location": "euw3-az1", "LocationType": "availability-zone-id"}, {"InstanceType": "m5a.16xlarge", "Location": "euw3-az2", "LocationType": "availability-zone-id"}, {"InstanceType": "t2.small", "Location": "euw3-az1", "LocationType": "availability-zone-id"}, {"InstanceType": "m5.8xlarge", "Location": "euw3-az3", "LocationType": "availability-zone-id"}, {"InstanceType": "c5d.9xlarge", "Location": "euw3-az3", "LocationType": "availability-zone-id"}, {"InstanceType": "c5n.metal", "Location": "euw3-az3", "LocationType": "availability-zone-id"}, {"InstanceType": "m5d.large", "Location": "euw3-az2", "LocationType": "availability-zone-id"}, {"InstanceType": "i3en.3xlarge", "Location": "euw3-az3", "LocationType": "availability-zone-id"}, {"InstanceType": "m5ad.2xlarge", "Location": "euw3-az1", "LocationType": "availability-zone-id"}, {"InstanceType": "m5.12xlarge", "Location": "euw3-az2", "LocationType": "availability-zone-id"}, {"InstanceType": "c5.18xlarge", "Location": "euw3-az3", "LocationType": "availability-zone-id"}, {"InstanceType": "i3en.24xlarge", "Location": "euw3-az3", "LocationType": "availability-zone-id"}, {"InstanceType": "r5.12xlarge", "Location": "euw3-az1", "LocationType": "availability-zone-id"}, {"InstanceType": "g4dn.8xlarge", "Location": "euw3-az1", "LocationType": "availability-zone-id"}, {"InstanceType": "r5d.8xlarge", "Location": "euw3-az1", "LocationType": "availability-zone-id"}, {"InstanceType": "i3.2xlarge", "Location": "euw3-az3", "LocationType": "availability-zone-id"}, {"InstanceType": "r5a.4xlarge", "Location": "euw3-az2", "LocationType": "availability-zone-id"}, {"InstanceType": "inf1.24xlarge", "Location": "euw3-az3", "LocationType": "availability-zone-id"}, {"InstanceType": "t2.small", "Location": "euw3-az2", "LocationType": "availability-zone-id"}, {"InstanceType": "t3a.medium", "Location": "euw3-az1", "LocationType": "availability-zone-id"}, {"InstanceType": "m5.xlarge", "Location": "euw3-az2", "LocationType": "availability-zone-id"}, {"InstanceType": "r5n.8xlarge", "Location": "euw3-az2", "LocationType": "availability-zone-id"}, {"InstanceType": "r5ad.24xlarge", "Location": "euw3-az3", "LocationType": "availability-zone-id"}, {"InstanceType": "g4dn.xlarge", "Location": "euw3-az1", "LocationType": "availability-zone-id"}, {"InstanceType": "i3.8xlarge", "Location": "euw3-az3", "LocationType": "availability-zone-id"}, {"InstanceType": "r4.8xlarge", "Location": "euw3-az3", "LocationType": "availability-zone-id"}, {"InstanceType": "c5n.9xlarge", "Location": "euw3-az3", "LocationType": "availability-zone-id"}, {"InstanceType": "i3en.3xlarge", "Location": "euw3-az2", "LocationType": "availability-zone-id"}, {"InstanceType": "r4.xlarge", "Location": "euw3-az2", "LocationType": "availability-zone-id"}, {"InstanceType": "m5ad.large", "Location": "euw3-az1", "LocationType": "availability-zone-id"}, {"InstanceType": "c5.xlarge", "Location": "euw3-az1", "LocationType": "availability-zone-id"}, {"InstanceType": "r4.8xlarge", "Location": "euw3-az1", "LocationType": "availability-zone-id"}, {"InstanceType": "c5d.9xlarge", "Location": "euw3-az1", "LocationType": "availability-zone-id"}, {"InstanceType": "d2.4xlarge", "Location": "euw3-az2", "LocationType": "availability-zone-id"}, {"InstanceType": "i3.8xlarge", "Location": "euw3-az2", "LocationType": "availability-zone-id"}, {"InstanceType": "i3en.large", "Location": "euw3-az3", "LocationType": "availability-zone-id"}, {"InstanceType": "r4.xlarge", "Location": "euw3-az1", "LocationType": "availability-zone-id"}, {"InstanceType": "m5.12xlarge", "Location": "euw3-az1", "LocationType": "availability-zone-id"}, {"InstanceType": "m5d.12xlarge", "Location": "euw3-az2", "LocationType": "availability-zone-id"}, {"InstanceType": "c5n.2xlarge", "Location": "euw3-az2", "LocationType": "availability-zone-id"}, {"InstanceType": "x1.32xlarge", "Location": "euw3-az2", "LocationType": "availability-zone-id"}, {"InstanceType": "g4dn.xlarge", "Location": "euw3-az3", "LocationType": "availability-zone-id"}, {"InstanceType": "r5.16xlarge", "Location": "euw3-az2", "LocationType": "availability-zone-id"}, {"InstanceType": "t2.nano", "Location": "euw3-az2", "LocationType": "availability-zone-id"}, {"InstanceType": "r4.xlarge", "Location": "euw3-az3", "LocationType": "availability-zone-id"}, {"InstanceType": "c5d.large", "Location": "euw3-az2", "LocationType": "availability-zone-id"}, {"InstanceType": "t3a.large", "Location": "euw3-az3", "LocationType": "availability-zone-id"}, {"InstanceType": "c5n.4xlarge", "Location": "euw3-az3", "LocationType": "availability-zone-id"}, {"InstanceType": "r5.metal", "Location": "euw3-az2", "LocationType": "availability-zone-id"}, {"InstanceType": "r5d.12xlarge", "Location": "euw3-az1", "LocationType": "availability-zone-id"}, {"InstanceType": "d2.2xlarge", "Location": "euw3-az3", "LocationType": "availability-zone-id"}, {"InstanceType": "c5d.large", "Location": "euw3-az3", "LocationType": "availability-zone-id"}, {"InstanceType": "t2.xlarge", "Location": "euw3-az1", "LocationType": "availability-zone-id"}, {"InstanceType": "g4dn.xlarge", "Location": "euw3-az2", "LocationType": "availability-zone-id"}, {"InstanceType": "c5d.4xlarge", "Location": "euw3-az3", "LocationType": "availability-zone-id"}, {"InstanceType": "t3a.2xlarge", "Location": "euw3-az1", "LocationType": "availability-zone-id"}, {"InstanceType": "m5d.xlarge", "Location": "euw3-az1", "LocationType": "availability-zone-id"}, {"InstanceType": "i3en.large", "Location": "euw3-az1", "LocationType": "availability-zone-id"}, {"InstanceType": "r5.4xlarge", "Location": "euw3-az1", "LocationType": "availability-zone-id"}, {"InstanceType": "t3.nano", "Location": "euw3-az2", "LocationType": "availability-zone-id"}, {"InstanceType": "i3.metal", "Location": "euw3-az2", "LocationType": "availability-zone-id"}, {"InstanceType": "i3en.12xlarge", "Location": "euw3-az2", "LocationType": "availability-zone-id"}, {"InstanceType": "c5.large", "Location": "euw3-az2", "LocationType": "availability-zone-id"}, {"InstanceType": "c5d.xlarge", "Location": "euw3-az1", "LocationType": "availability-zone-id"}, {"InstanceType": "c5n.4xlarge", "Location": "euw3-az2", "LocationType": "availability-zone-id"}, {"InstanceType": "m5a.24xlarge", "Location": "euw3-az3", "LocationType": "availability-zone-id"}, {"InstanceType": "m5a.16xlarge", "Location": "euw3-az1", "LocationType": "availability-zone-id"}, {"InstanceType": "i3.metal", "Location": "euw3-az1", "LocationType": "availability-zone-id"}, {"InstanceType": "g4dn.4xlarge", "Location": "euw3-az1", "LocationType": "availability-zone-id"}, {"InstanceType": "d2.xlarge", "Location": "euw3-az2", "LocationType": "availability-zone-id"}, {"InstanceType": "x1.32xlarge", "Location": "euw3-az3", "LocationType": "availability-zone-id"}, {"InstanceType": "t3.small", "Location": "euw3-az1", "LocationType": "availability-zone-id"}, {"InstanceType": "i3en.24xlarge", "Location": "euw3-az2", "LocationType": "availability-zone-id"}, {"InstanceType": "t3.medium", "Location": "euw3-az2", "LocationType": "availability-zone-id"}, {"InstanceType": "t3.nano", "Location": "euw3-az3", "LocationType": "availability-zone-id"}, {"InstanceType": "r5ad.xlarge", "Location": "euw3-az2", "LocationType": "availability-zone-id"}, {"InstanceType": "r5.8xlarge", "Location": "euw3-az3", "LocationType": "availability-zone-id"}, {"InstanceType": "r5d.24xlarge", "Location": "euw3-az3", "LocationType": "availability-zone-id"}, {"InstanceType": "c5n.xlarge", "Location": "euw3-az2", "LocationType": "availability-zone-id"}, {"InstanceType": "m5.8xlarge", "Location": "euw3-az2", "LocationType": "availability-zone-id"}, {"InstanceType": "r5a.16xlarge", "Location": "euw3-az1", "LocationType": "availability-zone-id"}, {"InstanceType": "g4dn.16xlarge", "Location": "euw3-az3", "LocationType": "availability-zone-id"}, {"InstanceType": "r5.large", "Location": "euw3-az2", "LocationType": "availability-zone-id"}, {"InstanceType": "m5a.2xlarge", "Location": "euw3-az1", "LocationType": "availability-zone-id"}, {"InstanceType": "t2.medium", "Location": "euw3-az2", "LocationType": "availability-zone-id"}, {"InstanceType": "m5.16xlarge", "Location": "euw3-az1", "LocationType": "availability-zone-id"}, {"InstanceType": "c5.12xlarge", "Location": "euw3-az2", "LocationType": "availability-zone-id"}, {"InstanceType": "r5n.24xlarge", "Location": "euw3-az1", "LocationType": "availability-zone-id"}, {"InstanceType": "c5d.4xlarge", "Location": "euw3-az1", "LocationType": "availability-zone-id"}, {"InstanceType": "i3en.2xlarge", "Location": "euw3-az1", "LocationType": "availability-zone-id"}, {"InstanceType": "g4dn.metal", "Location": "euw3-az2", "LocationType": "availability-zone-id"}, {"InstanceType": "t3a.xlarge", "Location": "euw3-az1", "LocationType": "availability-zone-id"}, {"InstanceType": "m5ad.2xlarge", "Location": "euw3-az3", "LocationType": "availability-zone-id"}, {"InstanceType": "i3en.6xlarge", "Location": "euw3-az2", "LocationType": "availability-zone-id"}, {"InstanceType": "r5a.24xlarge", "Location": "euw3-az2", "LocationType": "availability-zone-id"}, {"InstanceType": "r5ad.4xlarge", "Location": "euw3-az1", "LocationType": "availability-zone-id"}, {"InstanceType": "i3.4xlarge", "Location": "euw3-az2", "LocationType": "availability-zone-id"}, {"InstanceType": "r5n.xlarge", "Location": "euw3-az1", "LocationType": "availability-zone-id"}, {"InstanceType": "r5ad.xlarge", "Location": "euw3-az3", "LocationType": "availability-zone-id"}, {"InstanceType": "r5.8xlarge", "Location": "euw3-az1", "LocationType": "availability-zone-id"}, {"InstanceType": "r5.4xlarge", "Location": "euw3-az2", "LocationType": "availability-zone-id"}, {"InstanceType": "c5.24xlarge", "Location": "euw3-az3", "LocationType": "availability-zone-id"}, {"InstanceType": "d2.4xlarge", "Location": "euw3-az1", "LocationType": "availability-zone-id"}, {"InstanceType": "r5a.xlarge", "Location": "euw3-az2", "LocationType": "availability-zone-id"}, {"InstanceType": "m5.4xlarge", "Location": "euw3-az3", "LocationType": "availability-zone-id"}, {"InstanceType": "t2.medium", "Location": "euw3-az3", "LocationType": "availability-zone-id"}, {"InstanceType": "r5d.24xlarge", "Location": "euw3-az2", "LocationType": "availability-zone-id"}, {"InstanceType": "m5.4xlarge", "Location": "euw3-az2", "LocationType": "availability-zone-id"}, {"InstanceType": "r4.8xlarge", "Location": "euw3-az2", "LocationType": "availability-zone-id"}, {"InstanceType": "m5a.large", "Location": "euw3-az1", "LocationType": "availability-zone-id"}, {"InstanceType": "m5.2xlarge", "Location": "euw3-az3", "LocationType": "availability-zone-id"}, {"InstanceType": "m5d.8xlarge", "Location": "euw3-az1", "LocationType": "availability-zone-id"}, {"InstanceType": "c5d.18xlarge", "Location": "euw3-az1", "LocationType": "availability-zone-id"}, {"InstanceType": "r5n.2xlarge", "Location": "euw3-az3", "LocationType": "availability-zone-id"}, {"InstanceType": "m5.24xlarge", "Location": "euw3-az3", "LocationType": "availability-zone-id"}, {"InstanceType": "x1.16xlarge", "Location": "euw3-az3", "LocationType": "availability-zone-id"}, {"InstanceType": "m5d.16xlarge", "Location": "euw3-az1", "LocationType": "availability-zone-id"}, {"InstanceType": "c5.xlarge", "Location": "euw3-az3", "LocationType": "availability-zone-id"}, {"InstanceType": "m5ad.xlarge", "Location": "euw3-az1", "LocationType": "availability-zone-id"}, {"InstanceType": "m5d.4xlarge", "Location": "euw3-az3", "LocationType": "availability-zone-id"}, {"InstanceType": "c5.24xlarge", "Location": "euw3-az1", "LocationType": "availability-zone-id"}, {"InstanceType": "i3.large", "Location": "euw3-az3", "LocationType": "availability-zone-id"}, {"InstanceType": "r5n.metal", "Location": "euw3-az3", "LocationType": "availability-zone-id"}, {"InstanceType": "c5.18xlarge", "Location": "euw3-az1", "LocationType": "availability-zone-id"}, {"InstanceType": "r5ad.2xlarge", "Location": "euw3-az3", "LocationType": "availability-zone-id"}, {"InstanceType": "g4dn.8xlarge", "Location": "euw3-az2", "LocationType": "availability-zone-id"}, {"InstanceType": "t3a.xlarge", "Location": "euw3-az3", "LocationType": "availability-zone-id"}, {"InstanceType": "m5d.16xlarge", "Location": "euw3-az2", "LocationType": "availability-zone-id"}, {"InstanceType": "i3en.2xlarge", "Location": "euw3-az3", "LocationType": "availability-zone-id"}, {"InstanceType": "d2.4xlarge", "Location": "euw3-az3", "LocationType": "availability-zone-id"}, {"InstanceType": "c5a.2xlarge", "Location": "euw3-az3", "LocationType": "availability-zone-id"}, {"InstanceType": "c5.24xlarge", "Location": "euw3-az2", "LocationType": "availability-zone-id"}, {"InstanceType": "inf1.xlarge", "Location": "euw3-az3", "LocationType": "availability-zone-id"}, {"InstanceType": "m5.2xlarge", "Location": "euw3-az2", "LocationType": "availability-zone-id"}, {"InstanceType": "c5a.2xlarge", "Location": "euw3-az1", "LocationType": "availability-zone-id"}, {"InstanceType": "r5.24xlarge", "Location": "euw3-az1", "LocationType": "availability-zone-id"}, {"InstanceType": "i3en.large", "Location": "euw3-az2", "LocationType": "availability-zone-id"}, {"InstanceType": "i3.2xlarge", "Location": "euw3-az2", "LocationType": "availability-zone-id"}, {"InstanceType": "t3.micro", "Location": "euw3-az1", "LocationType": "availability-zone-id"}, {"InstanceType": "m5.24xlarge", "Location": "euw3-az2", "LocationType": "availability-zone-id"}, {"InstanceType": "t3a.nano", "Location": "euw3-az2", "LocationType": "availability-zone-id"}, {"InstanceType": "m5ad.4xlarge", "Location": "euw3-az1", "LocationType": "availability-zone-id"}, {"InstanceType": "g4dn.16xlarge", "Location": "euw3-az2", "LocationType": "availability-zone-id"}, {"InstanceType": "t3.small", "Location": "euw3-az3", "LocationType": "availability-zone-id"}, {"InstanceType": "inf1.24xlarge", "Location": "euw3-az1", "LocationType": "availability-zone-id"}, {"InstanceType": "r5a.16xlarge", "Location": "euw3-az2", "LocationType": "availability-zone-id"}, {"InstanceType": "c5.18xlarge", "Location": "euw3-az2", "LocationType": "availability-zone-id"}, {"InstanceType": "c5.large", "Location": "euw3-az1", "LocationType": "availability-zone-id"}, {"InstanceType": "i3.xlarge", "Location": "euw3-az2", "LocationType": "availability-zone-id"}, {"InstanceType": "i3.xlarge", "Location": "euw3-az3", "LocationType": "availability-zone-id"}, {"InstanceType": "c5.9xlarge", "Location": "euw3-az2", "LocationType": "availability-zone-id"}, {"InstanceType": "i3.metal", "Location": "euw3-az3", "LocationType": "availability-zone-id"}, {"InstanceType": "c5a.16xlarge", "Location": "euw3-az3", "LocationType": "availability-zone-id"}, {"InstanceType": "r5ad.16xlarge", "Location": "euw3-az3", "LocationType": "availability-zone-id"}, {"InstanceType": "r5d.large", "Location": "euw3-az2", "LocationType": "availability-zone-id"}, {"InstanceType": "r5.16xlarge", "Location": "euw3-az1", "LocationType": "availability-zone-id"}, {"InstanceType": "r5.24xlarge", "Location": "euw3-az3", "LocationType": "availability-zone-id"}, {"InstanceType": "r5n.24xlarge", "Location": "euw3-az3", "LocationType": "availability-zone-id"}, {"InstanceType": "c5.xlarge", "Location": "euw3-az2", "LocationType": "availability-zone-id"}, {"InstanceType": "r5.xlarge", "Location": "euw3-az3", "LocationType": "availability-zone-id"}, {"InstanceType": "t2.large", "Location": "euw3-az3", "LocationType": "availability-zone-id"}, {"InstanceType": "inf1.xlarge", "Location": "euw3-az1", "LocationType": "availability-zone-id"}, {"InstanceType": "c5n.metal", "Location": "euw3-az1", "LocationType": "availability-zone-id"}, {"InstanceType": "t3a.2xlarge", "Location": "euw3-az3", "LocationType": "availability-zone-id"}, {"InstanceType": "m5d.metal", "Location": "euw3-az2", "LocationType": "availability-zone-id"}, {"InstanceType": "m5ad.8xlarge", "Location": "euw3-az2", "LocationType": "availability-zone-id"}, {"InstanceType": "m5.2xlarge", "Location": "euw3-az1", "LocationType": "availability-zone-id"}, {"InstanceType": "r5.2xlarge", "Location": "euw3-az3", "LocationType": "availability-zone-id"}, {"InstanceType": "r5d.metal", "Location": "euw3-az3", "LocationType": "availability-zone-id"}, {"InstanceType": "g4dn.12xlarge", "Location": "euw3-az2", "LocationType": "availability-zone-id"}, {"InstanceType": "m5a.large", "Location": "euw3-az2", "LocationType": "availability-zone-id"}, {"InstanceType": "c5d.2xlarge", "Location": "euw3-az2", "LocationType": "availability-zone-id"}, {"InstanceType": "t3a.micro", "Location": "euw3-az2", "LocationType": "availability-zone-id"}, {"InstanceType": "r5n.4xlarge", "Location": "euw3-az3", "LocationType": "availability-zone-id"}, {"InstanceType": "r5ad.12xlarge", "Location": "euw3-az3", "LocationType": "availability-zone-id"}, {"InstanceType": "t2.2xlarge", "Location": "euw3-az3", "LocationType": "availability-zone-id"}, {"InstanceType": "m5.metal", "Location": "euw3-az2", "LocationType": "availability-zone-id"}, {"InstanceType": "r5n.2xlarge", "Location": "euw3-az1", "LocationType": "availability-zone-id"}, {"InstanceType": "r4.4xlarge", "Location": "euw3-az3", "LocationType": "availability-zone-id"}, {"InstanceType": "c5n.large", "Location": "euw3-az3", "LocationType": "availability-zone-id"}, {"InstanceType": "r5ad.12xlarge", "Location": "euw3-az2", "LocationType": "availability-zone-id"}, {"InstanceType": "t3a.medium", "Location": "euw3-az2", "LocationType": "availability-zone-id"}, {"InstanceType": "inf1.2xlarge", "Location": "euw3-az3", "LocationType": "availability-zone-id"}, {"InstanceType": "r5.large", "Location": "euw3-az1", "LocationType": "availability-zone-id"}, {"InstanceType": "c5n.9xlarge", "Location": "euw3-az1", "LocationType": "availability-zone-id"}, {"InstanceType": "m5d.metal", "Location": "euw3-az3", "LocationType": "availability-zone-id"}, {"InstanceType": "r5n.4xlarge", "Location": "euw3-az2", "LocationType": "availability-zone-id"}, {"InstanceType": "c5a.4xlarge", "Location": "euw3-az3", "LocationType": "availability-zone-id"}, {"InstanceType": "t2.large", "Location": "euw3-az2", "LocationType": "availability-zone-id"}, {"InstanceType": "r5d.2xlarge", "Location": "euw3-az1", "LocationType": "availability-zone-id"}, {"InstanceType": "c5.4xlarge", "Location": "euw3-az1", "LocationType": "availability-zone-id"}, {"InstanceType": "t3a.small", "Location": "euw3-az1", "LocationType": "availability-zone-id"}, {"InstanceType": "r5a.large", "Location": "euw3-az2", "LocationType": "availability-zone-id"}, {"InstanceType": "t3.medium", "Location": "euw3-az3", "LocationType": "availability-zone-id"}, {"InstanceType": "r5.metal", "Location": "euw3-az1", "LocationType": "availability-zone-id"}, {"InstanceType": "r5a.xlarge", "Location": "euw3-az3", "LocationType": "availability-zone-id"}, {"InstanceType": "c5d.4xlarge", "Location": "euw3-az2", "LocationType": "availability-zone-id"}, {"InstanceType": "c5n.xlarge", "Location": "euw3-az1", "LocationType": "availability-zone-id"}, {"InstanceType": "d2.8xlarge", "Location": "euw3-az2", "LocationType": "availability-zone-id"}, {"InstanceType": "r5a.xlarge", "Location": "euw3-az1", "LocationType": "availability-zone-id"}, {"InstanceType": "m5.24xlarge", "Location": "euw3-az1", "LocationType": "availability-zone-id"}, {"InstanceType": "c5d.9xlarge", "Location": "euw3-az2", "LocationType": "availability-zone-id"}, {"InstanceType": "c5.12xlarge", "Location": "euw3-az1", "LocationType": "availability-zone-id"}, {"InstanceType": "c5n.metal", "Location": "euw3-az2", "LocationType": "availability-zone-id"}, {"InstanceType": "r5d.16xlarge", "Location": "euw3-az1", "LocationType": "availability-zone-id"}, {"InstanceType": "r5d.12xlarge", "Location": "euw3-az3", "LocationType": "availability-zone-id"}, {"InstanceType": "r5a.4xlarge", "Location": "euw3-az1", "LocationType": "availability-zone-id"}, {"InstanceType": "m5d.2xlarge", "Location": "euw3-az3", "LocationType": "availability-zone-id"}, {"InstanceType": "t2.micro", "Location": "euw3-az2", "LocationType": "availability-zone-id"}, {"InstanceType": "r5ad.xlarge", "Location": "euw3-az1", "LocationType": "availability-zone-id"}, {"InstanceType": "m5.xlarge", "Location": "euw3-az3", "LocationType": "availability-zone-id"}, {"InstanceType": "m5ad.12xlarge", "Location": "euw3-az3", "LocationType": "availability-zone-id"}, {"InstanceType": "r5ad.16xlarge", "Location": "euw3-az2", "LocationType": "availability-zone-id"}, {"InstanceType": "c5n.large", "Location": "euw3-az2", "LocationType": "availability-zone-id"}, {"InstanceType": "r5n.xlarge", "Location": "euw3-az2", "LocationType": "availability-zone-id"}, {"InstanceType": "r5d.8xlarge", "Location": "euw3-az3", "LocationType": "availability-zone-id"}, {"InstanceType": "r5n.2xlarge", "Location": "euw3-az2", "LocationType": "availability-zone-id"}, {"InstanceType": "i3en.6xlarge", "Location": "euw3-az3", "LocationType": "availability-zone-id"}, {"InstanceType": "d2.8xlarge", "Location": "euw3-az1", "LocationType": "availability-zone-id"}, {"InstanceType": "r5n.16xlarge", "Location": "euw3-az2", "LocationType": "availability-zone-id"}, {"InstanceType": "r5a.24xlarge", "Location": "euw3-az1", "LocationType": "availability-zone-id"}, {"InstanceType": "t3a.medium", "Location": "euw3-az3", "LocationType": "availability-zone-id"}, {"InstanceType": "d2.xlarge", "Location": "euw3-az1", "LocationType": "availability-zone-id"}, {"InstanceType": "c5a.12xlarge", "Location": "euw3-az3", "LocationType": "availability-zone-id"}, {"InstanceType": "i3.16xlarge", "Location": "euw3-az2", "LocationType": "availability-zone-id"}, {"InstanceType": "m5d.4xlarge", "Location": "euw3-az2", "LocationType": "availability-zone-id"}, {"InstanceType": "r5.large", "Location": "euw3-az3", "LocationType": "availability-zone-id"}, {"InstanceType": "r5n.large", "Location": "euw3-az2", "LocationType": "availability-zone-id"}, {"InstanceType": "t3.large", "Location": "euw3-az3", "LocationType": "availability-zone-id"}, {"InstanceType": "c5d.18xlarge", "Location": "euw3-az2", "LocationType": "availability-zone-id"}, {"InstanceType": "r5ad.large", "Location": "euw3-az2", "LocationType": "availability-zone-id"}, {"InstanceType": "t3.xlarge", "Location": "euw3-az3", "LocationType": "availability-zone-id"}, {"InstanceType": "r5ad.8xlarge", "Location": "euw3-az1", "LocationType": "availability-zone-id"}, {"InstanceType": "r5a.2xlarge", "Location": "euw3-az2", "LocationType": "availability-zone-id"}, {"InstanceType": "i3en.xlarge", "Location": "euw3-az3", "LocationType": "availability-zone-id"}, {"InstanceType": "t2.micro", "Location": "euw3-az1", "LocationType": "availability-zone-id"}, {"InstanceType": "i3en.xlarge", "Location": "euw3-az1", "LocationType": "availability-zone-id"}, {"InstanceType": "t3.xlarge", "Location": "euw3-az1", "LocationType": "availability-zone-id"}, {"InstanceType": "t3a.small", "Location": "euw3-az2", "LocationType": "availability-zone-id"}, {"InstanceType": "m5ad.4xlarge", "Location": "euw3-az2", "LocationType": "availability-zone-id"}, {"InstanceType": "r5a.12xlarge", "Location": "euw3-az1", "LocationType": "availability-zone-id"}, {"InstanceType": "r5n.metal", "Location": "euw3-az2", "LocationType": "availability-zone-id"}, {"InstanceType": "r5ad.4xlarge", "Location": "euw3-az2", "LocationType": "availability-zone-id"}, {"InstanceType": "i3.xlarge", "Location": "euw3-az1", "LocationType": "availability-zone-id"}, {"InstanceType": "m5d.24xlarge", "Location": "euw3-az3", "LocationType": "availability-zone-id"}, {"InstanceType": "t2.nano", "Location": "euw3-az3", "LocationType": "availability-zone-id"}, {"InstanceType": "r5n.12xlarge", "Location": "euw3-az3", "LocationType": "availability-zone-id"}, {"InstanceType": "i3.16xlarge", "Location": "euw3-az3", "LocationType": "availability-zone-id"}, {"InstanceType": "m5ad.xlarge", "Location": "euw3-az3", "LocationType": "availability-zone-id"}, {"InstanceType": "c5.large", "Location": "euw3-az3", "LocationType": "availability-zone-id"}, {"InstanceType": "m5a.8xlarge", "Location": "euw3-az3", "LocationType": "availability-zone-id"}, {"InstanceType": "r4.4xlarge", "Location": "euw3-az1", "LocationType": "availability-zone-id"}, {"InstanceType": "r4.16xlarge", "Location": "euw3-az3", "LocationType": "availability-zone-id"}, {"InstanceType": "r5d.4xlarge", "Location": "euw3-az1", "LocationType": "availability-zone-id"}, {"InstanceType": "d2.xlarge", "Location": "euw3-az3", "LocationType": "availability-zone-id"}, {"InstanceType": "i3en.3xlarge", "Location": "euw3-az1", "LocationType": "availability-zone-id"}, {"InstanceType": "r5d.metal", "Location": "euw3-az1", "LocationType": "availability-zone-id"}, {"InstanceType": "r5d.large", "Location": "euw3-az1", "LocationType": "availability-zone-id"}, {"InstanceType": "r5a.8xlarge", "Location": "euw3-az3", "LocationType": "availability-zone-id"}, {"InstanceType": "m5a.2xlarge", "Location": "euw3-az2", "LocationType": "availability-zone-id"}, {"InstanceType": "c5n.4xlarge", "Location": "euw3-az1", "LocationType": "availability-zone-id"}, {"InstanceType": "m5ad.2xlarge", "Location": "euw3-az2", "LocationType": "availability-zone-id"}, {"InstanceType": "t3.small", "Location": "euw3-az2", "LocationType": "availability-zone-id"}, {"InstanceType": "g4dn.12xlarge", "Location": "euw3-az3", "LocationType": "availability-zone-id"}, {"InstanceType": "m5ad.4xlarge", "Location": "euw3-az3", "LocationType": "availability-zone-id"}, {"InstanceType": "c5d.2xlarge", "Location": "euw3-az1", "LocationType": "availability-zone-id"}, {"InstanceType": "c5a.16xlarge", "Location": "euw3-az1", "LocationType": "availability-zone-id"}, {"InstanceType": "i3.large", "Location": "euw3-az1", "LocationType": "availability-zone-id"}, {"InstanceType": "c5n.18xlarge", "Location": "euw3-az1", "LocationType": "availability-zone-id"}, {"InstanceType": "g4dn.2xlarge", "Location": "euw3-az2", "LocationType": "availability-zone-id"}, {"InstanceType": "r5.12xlarge", "Location": "euw3-az2", "LocationType": "availability-zone-id"}, {"InstanceType": "r5n.large", "Location": "euw3-az1", "LocationType": "availability-zone-id"}, {"InstanceType": "m5a.xlarge", "Location": "euw3-az3", "LocationType": "availability-zone-id"}, {"InstanceType": "i3en.24xlarge", "Location": "euw3-az1", "LocationType": "availability-zone-id"}, {"InstanceType": "t2.micro", "Location": "euw3-az3", "LocationType": "availability-zone-id"}, {"InstanceType": "i3en.2xlarge", "Location": "euw3-az2", "LocationType": "availability-zone-id"}, {"InstanceType": "r5a.large", "Location": "euw3-az3", "LocationType": "availability-zone-id"}, {"InstanceType": "m5d.large", "Location": "euw3-az1", "LocationType": "availability-zone-id"}, {"InstanceType": "c5n.9xlarge", "Location": "euw3-az2", "LocationType": "availability-zone-id"}, {"InstanceType": "r5d.xlarge", "Location": "euw3-az2", "LocationType": "availability-zone-id"}, {"InstanceType": "t3.large", "Location": "euw3-az2", "LocationType": "availability-zone-id"}, {"InstanceType": "r5.8xlarge", "Location": "euw3-az2", "LocationType": "availability-zone-id"}, {"InstanceType": "r5a.8xlarge", "Location": "euw3-az2", "LocationType": "availability-zone-id"}, {"InstanceType": "r5d.2xlarge", "Location": "euw3-az3", "LocationType": "availability-zone-id"}, {"InstanceType": "r5n.24xlarge", "Location": "euw3-az2", "LocationType": "availability-zone-id"}, {"InstanceType": "r5a.8xlarge", "Location": "euw3-az1", "LocationType": "availability-zone-id"}, {"InstanceType": "m5ad.large", "Location": "euw3-az2", "LocationType": "availability-zone-id"}, {"InstanceType": "r5n.4xlarge", "Location": "euw3-az1", "LocationType": "availability-zone-id"}, {"InstanceType": "g4dn.2xlarge", "Location": "euw3-az3", "LocationType": "availability-zone-id"}, {"InstanceType": "r4.2xlarge", "Location": "euw3-az1", "LocationType": "availability-zone-id"}, {"InstanceType": "r5a.large", "Location": "euw3-az1", "LocationType": "availability-zone-id"}, {"InstanceType": "m5d.2xlarge", "Location": "euw3-az1", "LocationType": "availability-zone-id"}, {"InstanceType": "r5ad.8xlarge", "Location": "euw3-az3", "LocationType": "availability-zone-id"}, {"InstanceType": "g4dn.4xlarge", "Location": "euw3-az3", "LocationType": "availability-zone-id"}, {"InstanceType": "r4.2xlarge", "Location": "euw3-az3", "LocationType": "availability-zone-id"}, {"InstanceType": "t3a.xlarge", "Location": "euw3-az2", "LocationType": "availability-zone-id"}, {"InstanceType": "m5.large", "Location": "euw3-az1", "LocationType": "availability-zone-id"}, {"InstanceType": "c5n.2xlarge", "Location": "euw3-az1", "LocationType": "availability-zone-id"}, {"InstanceType": "c5.2xlarge", "Location": "euw3-az3", "LocationType": "availability-zone-id"}, {"InstanceType": "r5ad.24xlarge", "Location": "euw3-az1", "LocationType": "availability-zone-id"}, {"InstanceType": "m5ad.12xlarge", "Location": "euw3-az2", "LocationType": "availability-zone-id"}, {"InstanceType": "m5.4xlarge", "Location": "euw3-az1", "LocationType": "availability-zone-id"}, {"InstanceType": "m5.large", "Location": "euw3-az2", "LocationType": "availability-zone-id"}, {"InstanceType": "m5a.4xlarge", "Location": "euw3-az1", "LocationType": "availability-zone-id"}, {"InstanceType": "c5a.24xlarge", "Location": "euw3-az1", "LocationType": "availability-zone-id"}, {"InstanceType": "g4dn.metal", "Location": "euw3-az1", "LocationType": "availability-zone-id"}, {"InstanceType": "c5n.large", "Location": "euw3-az1", "LocationType": "availability-zone-id"}, {"InstanceType": "r5d.4xlarge", "Location": "euw3-az3", "LocationType": "availability-zone-id"}, {"InstanceType": "r4.16xlarge", "Location": "euw3-az1", "LocationType": "availability-zone-id"}, {"InstanceType": "r5ad.16xlarge", "Location": "euw3-az1", "LocationType": "availability-zone-id"}, {"InstanceType": "inf1.6xlarge", "Location": "euw3-az3", "LocationType": "availability-zone-id"}, {"InstanceType": "m5a.12xlarge", "Location": "euw3-az1", "LocationType": "availability-zone-id"}, {"InstanceType": "inf1.6xlarge", "Location": "euw3-az1", "LocationType": "availability-zone-id"}, {"InstanceType": "r5d.large", "Location": "euw3-az3", "LocationType": "availability-zone-id"}, {"InstanceType": "r5d.16xlarge", "Location": "euw3-az2", "LocationType": "availability-zone-id"}, {"InstanceType": "m5d.12xlarge", "Location": "euw3-az3", "LocationType": "availability-zone-id"}, {"InstanceType": "c5n.xlarge", "Location": "euw3-az3", "LocationType": "availability-zone-id"}, {"InstanceType": "m5a.large", "Location": "euw3-az3", "LocationType": "availability-zone-id"}, {"InstanceType": "c5a.large", "Location": "euw3-az3", "LocationType": "availability-zone-id"}, {"InstanceType": "c5.4xlarge", "Location": "euw3-az2", "LocationType": "availability-zone-id"}, {"InstanceType": "m5ad.8xlarge", "Location": "euw3-az1", "LocationType": "availability-zone-id"}, {"InstanceType": "m5.16xlarge", "Location": "euw3-az3", "LocationType": "availability-zone-id"}, {"InstanceType": "i3en.12xlarge", "Location": "euw3-az1", "LocationType": "availability-zone-id"}, {"InstanceType": "m5ad.large", "Location": "euw3-az3", "LocationType": "availability-zone-id"}, {"InstanceType": "g4dn.16xlarge", "Location": "euw3-az1", "LocationType": "availability-zone-id"}, {"InstanceType": "t3.2xlarge", "Location": "euw3-az2", "LocationType": "availability-zone-id"}, {"InstanceType": "r5ad.large", "Location": "euw3-az3", "LocationType": "availability-zone-id"}, {"InstanceType": "r5n.metal", "Location": "euw3-az1", "LocationType": "availability-zone-id"}, {"InstanceType": "t3a.nano", "Location": "euw3-az3", "LocationType": "availability-zone-id"}, {"InstanceType": "m5ad.8xlarge", "Location": "euw3-az3", "LocationType": "availability-zone-id"}, {"InstanceType": "c5d.18xlarge", "Location": "euw3-az3", "LocationType": "availability-zone-id"}, {"InstanceType": "t3a.nano", "Location": "euw3-az1", "LocationType": "availability-zone-id"}, {"InstanceType": "c5.metal", "Location": "euw3-az1", "LocationType": "availability-zone-id"}, {"InstanceType": "i3.4xlarge", "Location": "euw3-az3", "LocationType": "availability-zone-id"}, {"InstanceType": "m5a.16xlarge", "Location": "euw3-az3", "LocationType": "availability-zone-id"}, {"InstanceType": "m5d.xlarge", "Location": "euw3-az3", "LocationType": "availability-zone-id"}, {"InstanceType": "m5a.8xlarge", "Location": "euw3-az1", "LocationType": "availability-zone-id"}, {"InstanceType": "m5d.16xlarge", "Location": "euw3-az3", "LocationType": "availability-zone-id"}, {"InstanceType": "r5n.16xlarge", "Location": "euw3-az3", "LocationType": "availability-zone-id"}]